Workbook
Name SelCat: Dashboard!$B$6
Name CatCrit: IF(Dashboard!$B$6="All","*",Dashboard!$B$6)

Sheet Dashboard
B1: SHELLY
B2: Consumer electronics report
B3: Demo data · industry pack
B5: Category
B6: All
B7: Change the blue cell to filter the whole workbook.
B9: UNITS | E9: REVENUE | H9: GROSS MARGIN | K9: GM %
B10: =SUMIFS(Raw!$E$2:$E$937,Raw!$D$2:$D$937,CatCrit) -> 4928 | E10: =SUMIFS(Raw!$F$2:$F$937,Raw!$D$2:$D$937,CatCrit) -> 3955026.2 | H10: =SUMIFS(Raw!$H$2:$H$937,Raw!$D$2:$D$937,CatCrit) -> 599343.23 | K10: =IFERROR(SUMIFS(Raw!$H$2:$H$937,Raw!$D$2:$D$937,CatCrit)/SUMIFS(Raw!$F$2:$F$937,Raw!$D$2:$D$937,CatCrit),0) -> 0.15153963

Sheet Model
B1: SHELLY
B2: Model
B3: Live formulas over Raw, Lookup and Assumptions. Nothing on this sheet is typed in.
B5: By category
B7: Category | C7: Units | D7: Revenue | E7: Gross margin | F7: GM %
B8: Accessory | C8: =SUMIFS(Raw!$E$2:$E$937,Raw!$D$2:$D$937,$B8) -> 385 | D8: =SUMIFS(Raw!$F$2:$F$937,Raw!$D$2:$D$937,$B8) -> 19286.93 | E8: =SUMIFS(Raw!$H$2:$H$937,Raw!$D$2:$D$937,$B8) -> 10903.93 | F8: =IFERROR(SUMIFS(Raw!$H$2:$H$937,Raw!$D$2:$D$937,$B8)/SUMIFS(Raw!$F$2:$F$937,Raw!$D$2:$D$937,$B8),0) -> 0.56535332
B9: Headphones | C9: =SUMIFS(Raw!$E$2:$E$937,Raw!$D$2:$D$937,$B9) -> 1228 | D9: =SUMIFS(Raw!$F$2:$F$937,Raw!$D$2:$D$937,$B9) -> 280266.49 | E9: =SUMIFS(Raw!$H$2:$H$937,Raw!$D$2:$D$937,$B9) -> 94916.49 | F9: =IFERROR(SUMIFS(Raw!$H$2:$H$937,Raw!$D$2:$D$937,$B9)/SUMIFS(Raw!$F$2:$F$937,Raw!$D$2:$D$937,$B9),0) -> 0.33866514
B10: Smartphone | C10: =SUMIFS(Raw!$E$2:$E$937,Raw!$D$2:$D$937,$B10) -> 1370 | D10: =SUMIFS(Raw!$F$2:$F$937,Raw!$D$2:$D$937,$B10) -> 1739846.4 | E10: =SUMIFS(Raw!$H$2:$H$937,Raw!$D$2:$D$937,$B10) -> 165208.44 | F10: =IFERROR(SUMIFS(Raw!$H$2:$H$937,Raw!$D$2:$D$937,$B10)/SUMIFS(Raw!$F$2:$F$937,Raw!$D$2:$D$937,$B10),0) -> 0.094955759
B11: Soundbar | C11: =SUMIFS(Raw!$E$2:$E$937,Raw!$D$2:$D$937,$B11) -> 567 | D11: =SUMIFS(Raw!$F$2:$F$937,Raw!$D$2:$D$937,$B11) -> 322942.03 | E11: =SUMIFS(Raw!$H$2:$H$937,Raw!$D$2:$D$937,$B11) -> 83096.03 | F11: =IFERROR(SUMIFS(Raw!$H$2:$H$937,Raw!$D$2:$D$937,$B11)/SUMIFS(Raw!$F$2:$F$937,Raw!$D$2:$D$937,$B11),0) -> 0.25730943
B12: TV | C12: =SUMIFS(Raw!$E$2:$E$937,Raw!$D$2:$D$937,$B12) -> 834 | D12: =SUMIFS(Raw!$F$2:$F$937,Raw!$D$2:$D$937,$B12) -> 1101975 | E12: =SUMIFS(Raw!$H$2:$H$937,Raw!$D$2:$D$937,$B12) -> 175456.03 | F12: =IFERROR(SUMIFS(Raw!$H$2:$H$937,Raw!$D$2:$D$937,$B12)/SUMIFS(Raw!$F$2:$F$937,Raw!$D$2:$D$937,$B12),0) -> 0.15921961
B13: Tablet | C13: =SUMIFS(Raw!$E$2:$E$937,Raw!$D$2:$D$937,$B13) -> 544 | D13: =SUMIFS(Raw!$F$2:$F$937,Raw!$D$2:$D$937,$B13) -> 490709.31 | E13: =SUMIFS(Raw!$H$2:$H$937,Raw!$D$2:$D$937,$B13) -> 69762.31 | F13: =IFERROR(SUMIFS(Raw!$H$2:$H$937,Raw!$D$2:$D$937,$B13)/SUMIFS(Raw!$F$2:$F$937,Raw!$D$2:$D$937,$B13),0) -> 0.14216627
B14: Total | C14: =SUM(C8:C13) -> 4928 | D14: =SUM(D8:D13) -> 3955026.2 | E14: =SUM(E8:E13) -> 599343.23
B17: By week (follows the selector)
B19: Week | C19: Units | D19: Revenue | E19: Gross margin
B20: 46110 | C20: =SUMIFS(Raw!$E$2:$E$937,Raw!$D$2:$D$937,CatCrit,Raw!$A$2:$A$937,$B20) -> 190 | D20: =SUMIFS(Raw!$F$2:$F$937,Raw!$D$2:$D$937,CatCrit,Raw!$A$2:$A$937,$B20) -> 154667 | E20: =SUMIFS(Raw!$H$2:$H$937,Raw!$D$2:$D$937,CatCrit,Raw!$A$2:$A$937,$B20) -> 27919
B21: 46117 | C21: =SUMIFS(Raw!$E$2:$E$937,Raw!$D$2:$D$937,CatCrit,Raw!$A$2:$A$937,$B21) -> 185 | D21: =SUMIFS(Raw!$F$2:$F$937,Raw!$D$2:$D$937,CatCrit,Raw!$A$2:$A$937,$B21) -> 148026.11 | E21: =SUMIFS(Raw!$H$2:$H$937,Raw!$D$2:$D$937,CatCrit,Raw!$A$2:$A$937,$B21) -> 27951.11
B22: 46124 | C22: =SUMIFS(Raw!$E$2:$E$937,Raw!$D$2:$D$937,CatCrit,Raw!$A$2:$A$937,$B22) -> 202 | D22: =SUMIFS(Raw!$F$2:$F$937,Raw!$D$2:$D$937,CatCrit,Raw!$A$2:$A$937,$B22) -> 172775.6 | E22: =SUMIFS(Raw!$H$2:$H$937,Raw!$D$2:$D$937,CatCrit,Raw!$A$2:$A$937,$B22) -> 29406.6
B23: 46131 | C23: =SUMIFS(Raw!$E$2:$E$937,Raw!$D$2:$D$937,CatCrit,Raw!$A$2:$A$937,$B23) -> 187 | D23: =SUMIFS(Raw!$F$2:$F$937,Raw!$D$2:$D$937,CatCrit,Raw!$A$2:$A$937,$B23) -> 164324.9 | E23: =SUMIFS(Raw!$H$2:$H$937,Raw!$D$2:$D$937,CatCrit,Raw!$A$2:$A$937,$B23) -> 26824.9
B24: 46138 | C24: =SUMIFS(Raw!$E$2:$E$937,Raw!$D$2:$D$937,CatCrit,Raw!$A$2:$A$937,$B24) -> 199 | D24: =SUMIFS(Raw!$F$2:$F$937,Raw!$D$2:$D$937,CatCrit,Raw!$A$2:$A$937,$B24) -> 157239.02 | E24: =SUMIFS(Raw!$H$2:$H$937,Raw!$D$2:$D$937,CatCrit,Raw!$A$2:$A$937,$B24) -> 27154.02
B25: 46145 | C25: =SUMIFS(Raw!$E$2:$E$937,Raw!$D$2:$D$937,CatCrit,Raw!$A$2:$A$937,$B25) -> 182 | D25: =SUMIFS(Raw!$F$2:$F$937,Raw!$D$2:$D$937,CatCrit,Raw!$A$2:$A$937,$B25) -> 154926.73 | E25: =SUMIFS(Raw!$H$2:$H$937,Raw!$D$2:$D$937,CatCrit,Raw!$A$2:$A$937,$B25) -> 26736.73
B26: 46152 | C26: =SUMIFS(Raw!$E$2:$E$937,Raw!$D$2:$D$937,CatCrit,Raw!$A$2:$A$937,$B26) -> 190 | D26: =SUMIFS(Raw!$F$2:$F$937,Raw!$D$2:$D$937,CatCrit,Raw!$A$2:$A$937,$B26) -> 156955.14 | E26: =SUMIFS(Raw!$H$2:$H$937,Raw!$D$2:$D$937,CatCrit,Raw!$A$2:$A$937,$B26) -> 26996.14
B27: 46159 | C27: =SUMIFS(Raw!$E$2:$E$937,Raw!$D$2:$D$937,CatCrit,Raw!$A$2:$A$937,$B27) -> 207 | D27: =SUMIFS(Raw!$F$2:$F$937,Raw!$D$2:$D$937,CatCrit,Raw!$A$2:$A$937,$B27) -> 173759.27 | E27: =SUMIFS(Raw!$H$2:$H$937,Raw!$D$2:$D$937,CatCrit,Raw!$A$2:$A$937,$B27) -> 27438.27
B28: 46166 | C28: =SUMIFS(Raw!$E$2:$E$937,Raw!$D$2:$D$937,CatCrit,Raw!$A$2:$A$937,$B28) -> 204 | D28: =SUMIFS(Raw!$F$2:$F$937,Raw!$D$2:$D$937,CatCrit,Raw!$A$2:$A$937,$B28) -> 163016.03 | E28: =SUMIFS(Raw!$H$2:$H$937,Raw!$D$2:$D$937,CatCrit,Raw!$A$2:$A$937,$B28) -> 27672.03
B29: 46173 | C29: =SUMIFS(Raw!$E$2:$E$937,Raw!$D$2:$D$937,CatCrit,Raw!$A$2:$A$937,$B29) -> 188 | D29: =SUMIFS(Raw!$F$2:$F$937,Raw!$D$2:$D$937,CatCrit,Raw!$A$2:$A$937,$B29) -> 147789.07 | E29: =SUMIFS(Raw!$H$2:$H$937,Raw!$D$2:$D$937,CatCrit,Raw!$A$2:$A$937,$B29) -> 23696.07
B30: 46180 | C30: =SUMIFS(Raw!$E$2:$E$937,Raw!$D$2:$D$937,CatCrit,Raw!$A$2:$A$937,$B30) -> 202 | D30: =SUMIFS(Raw!$F$2:$F$937,Raw!$D$2:$D$937,CatCrit,Raw!$A$2:$A$937,$B30) -> 161459.48 | E30: =SUMIFS(Raw!$H$2:$H$937,Raw!$D$2:$D$937,CatCrit,Raw!$A$2:$A$937,$B30) -> 24581.48
B31: 46187 | C31: =SUMIFS(Raw!$E$2:$E$937,Raw!$D$2:$D$937,CatCrit,Raw!$A$2:$A$937,$B31) -> 229 | D31: =SUMIFS(Raw!$F$2:$F$937,Raw!$D$2:$D$937,CatCrit,Raw!$A$2:$A$937,$B31) -> 196587.63 | E31: =SUMIFS(Raw!$H$2:$H$937,Raw!$D$2:$D$937,CatCrit,Raw!$A$2:$A$937,$B31) -> 28882.63
... B45: 46285 | C45: =SUMIFS(Raw!$E$2:$E$937,Raw!$D$2:$D$937,CatCrit,Raw!$A$2:$A$937,$B45) -> 163 | D45: =SUMIFS(Raw!$F$2:$F$937,Raw!$D$2:$D$937,CatCrit,Raw!$A$2:$A$937,$B45) -> 135173.06 | E45: =SUMIFS(Raw!$H$2:$H$937,Raw!$D$2:$D$937,CatCrit,Raw!$A$2:$A$937,$B45) -> 15636.06
B46: Total | C46: =SUM(C20:C45) -> 4928 | D46: =SUM(D20:D45) -> 3955026.2 | E46: =SUM(E20:E45) -> 599343.23

Sheet Pivot
B1: SHELLY
B2: Pivot tables
B3: Real Excel PivotTables over the Raw sheet: drag fields in the PivotTable pane to explore. They refresh when the file opens.
A5: Gross margin by category and week
A6: Row Labels | B6: Gross margin
A7: Accessory | B7: 10903.93
A8: Headphones | B8: 94916.49
A9: Smartphone | B9: 165208.44
A10: Soundbar | B10: 83096.03
A11: TV | B11: 175456.03
A12: Tablet | B12: 69762.31
A13: Grand Total | B13: 599343.23
A17: Units by week
A18: Row Labels | B18: Units
A19: 2026-03-29 | B19: 190
A20: 2026-04-05 | B20: 185
A21: 2026-04-12 | B21: 202
A22: 2026-04-19 | B22: 187
A23: 2026-04-26 | B23: 199
A24: 2026-05-03 | B24: 182
A25: 2026-05-10 | B25: 190
A26: 2026-05-17 | B26: 207
A27: 2026-05-24 | B27: 204
A28: 2026-05-31 | B28: 188
A29: 2026-06-07 | B29: 202
A30: 2026-06-14 | B30: 229
... A45: Grand Total | B45: 4928

Sheet Raw
A1: Week | B1: SKU | C1: Product | D1: Category | E1: Units | F1: Revenue | G1: Cost | H1: Gross margin
A2: 46110 | B2: TV01 | C2: TV model 1 | D2: TV | E2: 4 | F2: 6478.3 | G2: 5116 | H2: 1362.3
A3: 46117 | B3: TV01 | C3: TV model 1 | D3: TV | E3: 7 | F3: 11431.17 | G3: 8953 | H3: 2478.17
A4: 46124 | B4: TV01 | C4: TV model 1 | D4: TV | E4: 6 | F4: 9102.92 | G4: 7674 | H4: 1428.92
A5: 46131 | B5: TV01 | C5: TV model 1 | D5: TV | E5: 7 | F5: 10701.69 | G5: 8953 | H5: 1748.69
A6: 46138 | B6: TV01 | C6: TV model 1 | D6: TV | E6: 3 | F6: 4783.97 | G6: 3837 | H6: 946.97
A7: 46145 | B7: TV01 | C7: TV model 1 | D7: TV | E7: 7 | F7: 10889.7 | G7: 8953 | H7: 1936.7
A8: 46152 | B8: TV01 | C8: TV model 1 | D8: TV | E8: 6 | F8: 9033.09 | G8: 7674 | H8: 1359.09
A9: 46159 | B9: TV01 | C9: TV model 1 | D9: TV | E9: 9 | F9: 13747.5 | G9: 11511 | H9: 2236.5
A10: 46166 | B10: TV01 | C10: TV model 1 | D10: TV | E10: 6 | F10: 8946.66 | G10: 7674 | H10: 1272.66
A11: 46173 | B11: TV01 | C11: TV model 1 | D11: TV | E11: 8 | F11: 12545.79 | G11: 10232 | H11: 2313.79
A12: 46180 | B12: TV01 | C12: TV model 1 | D12: TV | E12: 5 | F12: 7804.26 | G12: 6395 | H12: 1409.26
A13: 46187 | B13: TV01 | C13: TV model 1 | D13: TV | E13: 4 | F13: 5996.11 | G13: 5116 | H13: 880.11
... A937: 46285 | B937: ACC06 | C937: Accessory model 6 | D937: Accessory | E937: 0 | F937: 0 | G937: 0 | H937: 0

Sheet Lookup
B1: SHELLY
B2: Lookup tables
B3: Reference data used by INDEX-MATCH formulas in the Model sheet.
M5: Category list
M6: All
M7: Accessory
M8: Headphones
M9: Smartphone
M10: Soundbar
M11: TV
M12: Tablet

Sheet Assumptions
B1: SHELLY
B2: Assumptions
B3: Blue cells are inputs: change them and every sheet recalculates.
B5: Input | C5: Value | D5: Why / source

Sheet Actions
B1: SHELLY
B2: Actions
B5: Priority | C5: Area | D5: Action | E5: Why | F5: Impact $/week | G5: Owner
B6: P2 | C6: Markdown | D6: Don't mark TV model 1 down 30% yet: ask the supplier for price protection or return-to-vendor, or bundle it; cap any markdown at 20% | E6: $65,229 at cost, 189 days old; a 30% markdown sells at -11% margin (below cost). Break-even markdown is 22% | F6: -1632 | G6: Category Manager
B7: P2 | C7: Markdown | D7: Mark down TV model 3 by 20% (154 days old) | E7: $44,362 at cost ageing; margin after markdown 3%; $/week = margin given up, spread over an 8-week sell-down | F7: -1109 | G7: Category Manager
B8: P2 | C8: Markdown | D8: Don't mark TV model 6 down 30% yet: ask the supplier for price protection or return-to-vendor, or bundle it; cap any markdown at 20% | E8: $42,021 at cost, 224 days old; a 30% markdown sells at -11% margin (below cost). Break-even markdown is 22% | F8: -1049 | G8: Category Manager
B9: P2 | C9: Markdown | D9: Mark down TV model 2 by 20% (168 days old) | E9: $37,200 at cost ageing; margin after markdown 3%; $/week = margin given up, spread over an 8-week sell-down | F9: -930 | G9: Category Manager
B10: P2 | C10: Markdown | D10: Don't mark Tablet model 3 down 30% yet: ask the supplier for price protection or return-to-vendor, or bundle it; cap any markdown at 18% | E10: $32,725 at cost, 182 days old; a 30% markdown sells at -14% margin (below cost). Break-even markdown is 20% | F10: -737 | G10: Category Manager
B11: P2 | C11: Markdown | D11: Mark down Smartphone model 6 by 10% (105 days old) | E11: $31,680 at cost ageing; margin after markdown 7%; $/week = margin given up, spread over an 8-week sell-down | F11: -396 | G11: Category Manager
B12: P2 | C12: Range & stock | D12: Stop reordering TV model 1 and plan a sell-down (15 weeks cover) | E12: 51 on hand, 14 sold in 4 weeks; ~$29,417 tied up above an 8-week target (holding cost ~0.5%/week) | F12: -147 | G12: Category Manager
B13: P2 | C13: Range & stock | D13: Stop reordering Tablet model 6 and plan a sell-down (40 weeks cover) | E13: 10 on hand, 1 sold in 4 weeks; ~$6,504 tied up above an 8-week target (holding cost ~0.5%/week) | F13: -33 | G13: Category Manager
B14: P2 | C14: Range & stock | D14: Stop reordering Headphones model 6 and plan a sell-down (12 weeks cover) | E14: 46 on hand, 15 sold in 4 weeks; ~$2,336 tied up above an 8-week target (holding cost ~0.5%/week) | F14: -12 | G14: Category Manager
B15: P2 | C15: Range & stock | D15: Stop reordering Soundbar model 6 and plan a sell-down (13 weeks cover) | E15: 13 on hand, 4 sold in 4 weeks; ~$2,315 tied up above an 8-week target (holding cost ~0.5%/week) | F15: -12 | G15: Category Manager
B16: P2 | C16: Range & stock | D16: Stop reordering Accessory model 6 and plan a sell-down (20 weeks cover) | E16: 25 on hand, 5 sold in 4 weeks; ~$300 tied up above an 8-week target (holding cost ~0.5%/week) | F16: -2 | G16: Category Manager
B17: P3 | C17: Attach | D17: Lift accessory attach from 11% towards 25% (bundles, till prompts, staff incentive) | E17: 39 accessories on 368 devices in 4 weeks | F17: 390 | G17: Store Manager
... B22: P3 | C22: Pricing | D22: Review TV pricing and promotion depth (ASP -5.5% in 26 weeks) | E22: price erosion beyond 5% squeezes margin unless volume grows faster | F22: 0 | G22: Category Manager

Sheet Sell-through & weeks of cover
B1: SHELLY
B2: Sell-through & weeks of cover
B5: name | C5: category | D5: on_hand | E5: units_4w | F5: sell_through_pct | G5: weeks_cover | H5: stock_value | I5: status
B6: Tablet model 6 | C6: Tablet | D6: 10 | E6: 1 | F6: 9.091 | G6: 40 | H6: 8130 | I6: Overstock
B7: Accessory model 6 | C7: Accessory | D7: 25 | E7: 5 | F7: 16.667 | G7: 20 | H7: 500 | I7: Overstock
B8: Accessory model 4 | C8: Accessory | D8: 19 | E8: 5 | F8: 20.833 | G8: 15.2 | H8: 361 | I8: Overstock
B9: TV model 1 | C9: TV | D9: 51 | E9: 14 | F9: 21.538 | G9: 14.571 | H9: 65229 | I9: Overstock
B10: Soundbar model 6 | C10: Soundbar | D10: 13 | E10: 4 | F10: 23.529 | G10: 13 | H10: 6019 | I10: Overstock
B11: Headphones model 6 | C11: Headphones | D11: 46 | E11: 15 | F11: 24.59 | G11: 12.267 | H11: 6716 | I11: Overstock
B12: Tablet model 2 | C12: Tablet | D12: 20 | E12: 7 | F12: 25.926 | G12: 11.429 | H12: 19860 | I12: OK
B13: Accessory model 5 | C13: Accessory | D13: 14 | E13: 5 | F13: 26.316 | G13: 11.2 | H13: 322 | I13: OK
B14: Tablet model 5 | C14: Tablet | D14: 30 | E14: 11 | F14: 26.829 | G14: 10.909 | H14: 20280 | I14: OK
B15: TV model 4 | C15: TV | D15: 51 | E15: 21 | F15: 29.167 | G15: 9.714 | H15: 54213 | I15: OK
B16: Smartphone model 6 | C16: Smartphone | D16: 30 | E16: 13 | F16: 30.233 | G16: 9.231 | H16: 31680 | I16: OK
B17: TV model 6 | C17: TV | D17: 29 | E17: 13 | F17: 30.952 | G17: 8.923 | H17: 42021 | I17: OK
... B41: Headphones model 4 | C41: Headphones | D41: 19 | E41: 33 | F41: 63.462 | G41: 2.303 | H41: 2432 | I41: OK

Sheet Aged stock & markdown ladder
B1: SHELLY
B2: Aged stock & markdown ladder
B5: band | C5: stock_value
B6: <90 | C6: 345854
B7: 90-120 | C7: 46344
B8: 120-180 | C8: 124911
B9: 180+ | C9: 201075

Sheet Price erosion ASP
B1: SHELLY
B2: Price erosion ASP
B5: category | C5: asp_then | D5: asp_now | E5: erosion_pct
B6: Accessory | C6: 51.7 | D6: 47.9 | E6: -7.2
B7: Headphones | C7: 233.5 | D7: 220.3 | E7: -5.6
B8: Smartphone | C8: 1321.6 | D8: 1228.7 | E8: -7
B9: Soundbar | C9: 569.3 | D9: 538.3 | E9: -5.4
B10: TV | C10: 1371.6 | D10: 1296.1 | E10: -5.5
B11: Tablet | C11: 885.6 | D11: 854.2 | E11: -3.5

Sheet Accessory attach rate
B1: SHELLY
B2: Accessory attach rate
B5: devices | C5: accessories | D5: attach_pct
B6: 368 | C6: 39 | D6: 10.6

Sheet Notes
B1: SHELLY
B2: Notes, method and sign-off
B3: How the numbers were made, what each column means, and who approved it.
B5: About this workbook
C6: Industry pack demo. Replace Raw with your own export (same column names) and the Model, KPIs and pivots follow.
C7: Analysis sheets hold Shelly's skill results; Actions lists findings for your confirmation.
B9: Data dictionary (Raw sheet)
B10: Week
B11: SKU
B12: Product
B13: Category
B14: Units
B15: Revenue
B16: Cost
B17: Gross margin
B19: Sign-off
B20: Findings reviewed | C20: Name: ____________ Date: ________ ☐ Approved ☐ Changes needed
B22: Generated by Shelly on 11 Oct 2026 21:21
