Workbook
Name SelCat: Dashboard!$B$6
Name CatCrit: IF(Dashboard!$B$6="All","*",Dashboard!$B$6)

Sheet Dashboard
B1: SHELLY
B2: Wholesale report
B3: Demo data · industry pack
B5: Customer
B6: All
B7: Change the blue cell to filter the whole workbook.
B9: REVENUE | E9: GROSS MARGIN | H9: GM %
B10: =SUMIFS(Raw!$E$2:$E$982,Raw!$D$2:$D$982,CatCrit) -> 726832.47 | E10: =SUMIFS(Raw!$G$2:$G$982,Raw!$D$2:$D$982,CatCrit) -> 99528.29 | H10: =IFERROR(SUMIFS(Raw!$G$2:$G$982,Raw!$D$2:$D$982,CatCrit)/SUMIFS(Raw!$E$2:$E$982,Raw!$D$2:$D$982,CatCrit),0) -> 0.13693429

Sheet Model
B1: SHELLY
B2: Model
B3: Live formulas over Raw, Lookup and Assumptions. Nothing on this sheet is typed in.
B5: By customer
B7: Customer | C7: Revenue | D7: Gross margin | E7: GM %
B8: City Cafe | C8: =SUMIFS(Raw!$E$2:$E$982,Raw!$D$2:$D$982,$B8) -> 53754.68 | D8: =SUMIFS(Raw!$G$2:$G$982,Raw!$D$2:$D$982,$B8) -> 9432.14 | E8: =IFERROR(SUMIFS(Raw!$G$2:$G$982,Raw!$D$2:$D$982,$B8)/SUMIFS(Raw!$E$2:$E$982,Raw!$D$2:$D$982,$B8),0) -> 0.1754664
B9: City Foods | C9: =SUMIFS(Raw!$E$2:$E$982,Raw!$D$2:$D$982,$B9) -> 24942.71 | D9: =SUMIFS(Raw!$G$2:$G$982,Raw!$D$2:$D$982,$B9) -> 2447.93 | E9: =IFERROR(SUMIFS(Raw!$G$2:$G$982,Raw!$D$2:$D$982,$B9)/SUMIFS(Raw!$E$2:$E$982,Raw!$D$2:$D$982,$B9),0) -> 0.098142102
B10: City Grocers | C10: =SUMIFS(Raw!$E$2:$E$982,Raw!$D$2:$D$982,$B10) -> 16270.27 | D10: =SUMIFS(Raw!$G$2:$G$982,Raw!$D$2:$D$982,$B10) -> 1578 | E10: =IFERROR(SUMIFS(Raw!$G$2:$G$982,Raw!$D$2:$D$982,$B10)/SUMIFS(Raw!$E$2:$E$982,Raw!$D$2:$D$982,$B10),0) -> 0.096986713
B11: City Mart | C11: =SUMIFS(Raw!$E$2:$E$982,Raw!$D$2:$D$982,$B11) -> 14781.02 | D11: =SUMIFS(Raw!$G$2:$G$982,Raw!$D$2:$D$982,$B11) -> 2032.96 | E11: =IFERROR(SUMIFS(Raw!$G$2:$G$982,Raw!$D$2:$D$982,$B11)/SUMIFS(Raw!$E$2:$E$982,Raw!$D$2:$D$982,$B11),0) -> 0.13753855
B12: City Superette | C12: =SUMIFS(Raw!$E$2:$E$982,Raw!$D$2:$D$982,$B12) -> 11245.53 | D12: =SUMIFS(Raw!$G$2:$G$982,Raw!$D$2:$D$982,$B12) -> 1162.83 | E12: =IFERROR(SUMIFS(Raw!$G$2:$G$982,Raw!$D$2:$D$982,$B12)/SUMIFS(Raw!$E$2:$E$982,Raw!$D$2:$D$982,$B12),0) -> 0.10340375
B13: Coast Cafe | C13: =SUMIFS(Raw!$E$2:$E$982,Raw!$D$2:$D$982,$B13) -> 9718.86 | D13: =SUMIFS(Raw!$G$2:$G$982,Raw!$D$2:$D$982,$B13) -> 970.62 | E13: =IFERROR(SUMIFS(Raw!$G$2:$G$982,Raw!$D$2:$D$982,$B13)/SUMIFS(Raw!$E$2:$E$982,Raw!$D$2:$D$982,$B13),0) -> 0.099869738
B14: Coast Foods | C14: =SUMIFS(Raw!$E$2:$E$982,Raw!$D$2:$D$982,$B14) -> 14061.24 | D14: =SUMIFS(Raw!$G$2:$G$982,Raw!$D$2:$D$982,$B14) -> 1357.87 | E14: =IFERROR(SUMIFS(Raw!$G$2:$G$982,Raw!$D$2:$D$982,$B14)/SUMIFS(Raw!$E$2:$E$982,Raw!$D$2:$D$982,$B14),0) -> 0.096568297
B15: Coast Grocers | C15: =SUMIFS(Raw!$E$2:$E$982,Raw!$D$2:$D$982,$B15) -> 32253.28 | D15: =SUMIFS(Raw!$G$2:$G$982,Raw!$D$2:$D$982,$B15) -> 4447.41 | E15: =IFERROR(SUMIFS(Raw!$G$2:$G$982,Raw!$D$2:$D$982,$B15)/SUMIFS(Raw!$E$2:$E$982,Raw!$D$2:$D$982,$B15),0) -> 0.13789016
B16: Coast Mart | C16: =SUMIFS(Raw!$E$2:$E$982,Raw!$D$2:$D$982,$B16) -> 11068.36 | D16: =SUMIFS(Raw!$G$2:$G$982,Raw!$D$2:$D$982,$B16) -> 1295.24 | E16: =IFERROR(SUMIFS(Raw!$G$2:$G$982,Raw!$D$2:$D$982,$B16)/SUMIFS(Raw!$E$2:$E$982,Raw!$D$2:$D$982,$B16),0) -> 0.11702185
B17: Coast Superette | C17: =SUMIFS(Raw!$E$2:$E$982,Raw!$D$2:$D$982,$B17) -> 5875.37 | D17: =SUMIFS(Raw!$G$2:$G$982,Raw!$D$2:$D$982,$B17) -> 904.24 | E17: =IFERROR(SUMIFS(Raw!$G$2:$G$982,Raw!$D$2:$D$982,$B17)/SUMIFS(Raw!$E$2:$E$982,Raw!$D$2:$D$982,$B17),0) -> 0.1539035
B18: Harbour Cafe | C18: =SUMIFS(Raw!$E$2:$E$982,Raw!$D$2:$D$982,$B18) -> 6119.11 | D18: =SUMIFS(Raw!$G$2:$G$982,Raw!$D$2:$D$982,$B18) -> 477.35 | E18: =IFERROR(SUMIFS(Raw!$G$2:$G$982,Raw!$D$2:$D$982,$B18)/SUMIFS(Raw!$E$2:$E$982,Raw!$D$2:$D$982,$B18),0) -> 0.078009711
B19: Harbour Foods | C19: =SUMIFS(Raw!$E$2:$E$982,Raw!$D$2:$D$982,$B19) -> 14378.56 | D19: =SUMIFS(Raw!$G$2:$G$982,Raw!$D$2:$D$982,$B19) -> 2822.22 | E19: =IFERROR(SUMIFS(Raw!$G$2:$G$982,Raw!$D$2:$D$982,$B19)/SUMIFS(Raw!$E$2:$E$982,Raw!$D$2:$D$982,$B19),0) -> 0.19627974
... B47: Valley Superette | C47: =SUMIFS(Raw!$E$2:$E$982,Raw!$D$2:$D$982,$B47) -> 31984.02 | D47: =SUMIFS(Raw!$G$2:$G$982,Raw!$D$2:$D$982,$B47) -> 6533.84 | E47: =IFERROR(SUMIFS(Raw!$G$2:$G$982,Raw!$D$2:$D$982,$B47)/SUMIFS(Raw!$E$2:$E$982,Raw!$D$2:$D$982,$B47),0) -> 0.20428451
B48: Total | C48: =SUM(C8:C47) -> 726832.47 | D48: =SUM(D8:D47) -> 99528.29
B51: By week (follows the selector)
B53: Week | C53: Revenue | D53: Gross margin
B54: 46195 | C54: =SUMIFS(Raw!$E$2:$E$982,Raw!$D$2:$D$982,CatCrit,Raw!$B$2:$B$982,$B54) -> 16182.49 | D54: =SUMIFS(Raw!$G$2:$G$982,Raw!$D$2:$D$982,CatCrit,Raw!$B$2:$B$982,$B54) -> 2467.99
B55: 46202 | C55: =SUMIFS(Raw!$E$2:$E$982,Raw!$D$2:$D$982,CatCrit,Raw!$B$2:$B$982,$B55) -> 38661.36 | D55: =SUMIFS(Raw!$G$2:$G$982,Raw!$D$2:$D$982,CatCrit,Raw!$B$2:$B$982,$B55) -> 4942.35
B56: 46209 | C56: =SUMIFS(Raw!$E$2:$E$982,Raw!$D$2:$D$982,CatCrit,Raw!$B$2:$B$982,$B56) -> 40847.06 | D56: =SUMIFS(Raw!$G$2:$G$982,Raw!$D$2:$D$982,CatCrit,Raw!$B$2:$B$982,$B56) -> 6237.93
B57: 46216 | C57: =SUMIFS(Raw!$E$2:$E$982,Raw!$D$2:$D$982,CatCrit,Raw!$B$2:$B$982,$B57) -> 78153.86 | D57: =SUMIFS(Raw!$G$2:$G$982,Raw!$D$2:$D$982,CatCrit,Raw!$B$2:$B$982,$B57) -> 9964.63
B58: 46223 | C58: =SUMIFS(Raw!$E$2:$E$982,Raw!$D$2:$D$982,CatCrit,Raw!$B$2:$B$982,$B58) -> 59898.92 | D58: =SUMIFS(Raw!$G$2:$G$982,Raw!$D$2:$D$982,CatCrit,Raw!$B$2:$B$982,$B58) -> 8228.4
B59: 46230 | C59: =SUMIFS(Raw!$E$2:$E$982,Raw!$D$2:$D$982,CatCrit,Raw!$B$2:$B$982,$B59) -> 57560.96 | D59: =SUMIFS(Raw!$G$2:$G$982,Raw!$D$2:$D$982,CatCrit,Raw!$B$2:$B$982,$B59) -> 7949.12
B60: 46237 | C60: =SUMIFS(Raw!$E$2:$E$982,Raw!$D$2:$D$982,CatCrit,Raw!$B$2:$B$982,$B60) -> 70451.83 | D60: =SUMIFS(Raw!$G$2:$G$982,Raw!$D$2:$D$982,CatCrit,Raw!$B$2:$B$982,$B60) -> 10602.78
B61: 46244 | C61: =SUMIFS(Raw!$E$2:$E$982,Raw!$D$2:$D$982,CatCrit,Raw!$B$2:$B$982,$B61) -> 47710.75 | D61: =SUMIFS(Raw!$G$2:$G$982,Raw!$D$2:$D$982,CatCrit,Raw!$B$2:$B$982,$B61) -> 6429.53
B62: 46251 | C62: =SUMIFS(Raw!$E$2:$E$982,Raw!$D$2:$D$982,CatCrit,Raw!$B$2:$B$982,$B62) -> 63322.95 | D62: =SUMIFS(Raw!$G$2:$G$982,Raw!$D$2:$D$982,CatCrit,Raw!$B$2:$B$982,$B62) -> 9325.67
B63: 46258 | C63: =SUMIFS(Raw!$E$2:$E$982,Raw!$D$2:$D$982,CatCrit,Raw!$B$2:$B$982,$B63) -> 61405.35 | D63: =SUMIFS(Raw!$G$2:$G$982,Raw!$D$2:$D$982,CatCrit,Raw!$B$2:$B$982,$B63) -> 7637.94
B64: 46265 | C64: =SUMIFS(Raw!$E$2:$E$982,Raw!$D$2:$D$982,CatCrit,Raw!$B$2:$B$982,$B64) -> 54789.96 | D64: =SUMIFS(Raw!$G$2:$G$982,Raw!$D$2:$D$982,CatCrit,Raw!$B$2:$B$982,$B64) -> 7324.26
B65: 46272 | C65: =SUMIFS(Raw!$E$2:$E$982,Raw!$D$2:$D$982,CatCrit,Raw!$B$2:$B$982,$B65) -> 40567.64 | D65: =SUMIFS(Raw!$G$2:$G$982,Raw!$D$2:$D$982,CatCrit,Raw!$B$2:$B$982,$B65) -> 5074.64
... B67: 46286 | C67: =SUMIFS(Raw!$E$2:$E$982,Raw!$D$2:$D$982,CatCrit,Raw!$B$2:$B$982,$B67) -> 40220.22 | D67: =SUMIFS(Raw!$G$2:$G$982,Raw!$D$2:$D$982,CatCrit,Raw!$B$2:$B$982,$B67) -> 5540.52
B68: Total | C68: =SUM(C54:C67) -> 726832.47 | D68: =SUM(D54:D67) -> 99528.29

Sheet Pivot
B1: SHELLY
B2: Pivot tables
B3: Real Excel PivotTables over the Raw sheet: drag fields in the PivotTable pane to explore. They refresh when the file opens.
A5: Gross margin by customer and week
A6: Row Labels | B6: Gross margin
A7: City Cafe | B7: 9432.14
A8: City Foods | B8: 2447.93
A9: City Grocers | B9: 1578
A10: City Mart | B10: 2032.96
A11: City Superette | B11: 1162.83
A12: Coast Cafe | B12: 970.62
A13: Coast Foods | B13: 1357.87
A14: Coast Grocers | B14: 4447.41
A15: Coast Mart | B15: 1295.24
A16: Coast Superette | B16: 904.24
A17: Harbour Cafe | B17: 477.35
A18: Harbour Foods | B18: 2822.22
... A47: Grand Total | B47: 99528.29
A51: Revenue by week
A52: Row Labels | B52: Revenue
A53: 2026-06-22 | B53: 16182.49
A54: 2026-06-29 | B54: 38661.36
A55: 2026-07-06 | B55: 40847.06
A56: 2026-07-13 | B56: 78153.86
A57: 2026-07-20 | B57: 59898.92
A58: 2026-07-27 | B58: 57560.96
A59: 2026-08-03 | B59: 70451.83
A60: 2026-08-10 | B60: 47710.75
A61: 2026-08-17 | B61: 63322.95
A62: 2026-08-24 | B62: 61405.35
A63: 2026-08-31 | B63: 54789.96
A64: 2026-09-07 | B64: 40567.64
... A67: Grand Total | B67: 726832.47

Sheet Raw
A1: Date | B1: Week | C1: Order | D1: Customer | E1: Revenue | F1: Cost | G1: Gross margin
A2: 46236 | B2: 46230 | C2: C001-0 | D2: Kiwi Foods | E2: 59.53 | F2: 52.87 | G2: 6.66
A3: 46207 | B3: 46202 | C3: C001-1 | D3: Kiwi Foods | E3: 74.19 | F3: 65.89 | G3: 8.3
A4: 46244 | B4: 46244 | C4: C001-2 | D4: Kiwi Foods | E4: 94.17 | F4: 83.63 | G4: 10.54
A5: 46244 | B5: 46244 | C5: C001-3 | D5: Kiwi Foods | E5: 63.29 | F5: 56.2 | G5: 7.09
A6: 46241 | B6: 46237 | C6: C001-4 | D6: Kiwi Foods | E6: 65.33 | F6: 58.02 | G6: 7.31
A7: 46218 | B7: 46216 | C7: C001-5 | D7: Kiwi Foods | E7: 68.1 | F7: 60.48 | G7: 7.62
A8: 46283 | B8: 46279 | C8: C001-6 | D8: Kiwi Foods | E8: 63.13 | F8: 56.07 | G8: 7.06
A9: 46209 | B9: 46209 | C9: C001-7 | D9: Kiwi Foods | E9: 109.8 | F9: 97.52 | G9: 12.28
A10: 46228 | B10: 46223 | C10: C001-8 | D10: Kiwi Foods | E10: 80.21 | F10: 71.23 | G10: 8.98
A11: 46228 | B11: 46223 | C11: C001-9 | D11: Kiwi Foods | E11: 70.19 | F11: 62.34 | G11: 7.85
A12: 46262 | B12: 46258 | C12: C001-10 | D12: Kiwi Foods | E12: 80.64 | F12: 71.62 | G12: 9.02
A13: 46279 | B13: 46279 | C13: C001-11 | D13: Kiwi Foods | E13: 109.12 | F13: 96.91 | G13: 12.21
... A982: 46203 | B982: 46202 | C982: C040-65 | D982: North Grocers | E982: 18.19 | F982: 16.04 | G982: 2.15

Sheet Lookup
B1: SHELLY
B2: Lookup tables
B3: Reference data used by INDEX-MATCH formulas in the Model sheet.
M5: Customer list
M6: All
M7: City Cafe
M8: City Foods
M9: City Grocers
M10: City Mart
M11: City Superette
M12: Coast Cafe
M13: Coast Foods
M14: Coast Grocers
M15: Coast Mart
M16: Coast Superette
... M46: Valley Superette

Sheet Assumptions
B1: SHELLY
B2: Assumptions
B3: Blue cells are inputs: change them and every sheet recalculates.
B5: Input | C5: Value | D5: Why / source

Sheet Actions
B1: SHELLY
B2: Actions
B5: Priority | C5: Area | D5: Action | E5: Why | F5: Impact $/week | G5: Owner
B6: P1 | C6: Credit | D6: Put Metro Foods on credit hold until 60+ day balance is cleared ($788) | E6: total owed $14,886; $788 is 60+ days overdue (exposure, not a weekly cost) | F6: 0 | G6: Finance
B7: P1 | C7: Credit | D7: Put Harbour Superette on credit hold until 60+ day balance is cleared ($1,382) | E7: total owed $12,816; $1,382 is 60+ days overdue (exposure, not a weekly cost) | F7: 0 | G7: Finance
B8: P1 | C8: Credit | D8: Put Coast Mart on credit hold until 60+ day balance is cleared ($1,402) | E8: total owed $4,993; $1,402 is 60+ days overdue (exposure, not a weekly cost) | F8: 0 | G8: Finance
B9: P2 | C9: Customer terms | D9: Review terms for North Grocers: minimum order or delivery fee (avg order $18) | E9: 66 orders in 90 days, margin $144 < cost-to-serve $1,188 | F9: 80 | G9: Sales Manager
B10: P2 | C10: Customer terms | D10: Review terms for Kiwi Mart: minimum order or delivery fee (avg order $63) | E10: 74 orders in 90 days, margin $301 < cost-to-serve $1,332 | F10: 79 | G10: Sales Manager
B11: P2 | C11: Customer terms | D11: Review terms for Kiwi Foods: minimum order or delivery fee (avg order $83) | E11: 50 orders in 90 days, margin $465 < cost-to-serve $900 | F11: 33 | G11: Sales Manager
B12: P2 | C12: Customer terms | D12: Review terms for Harbour Cafe: minimum order or delivery fee (avg order $219) | E12: 28 orders in 90 days, margin $477 < cost-to-serve $504 | F12: 2 | G12: Sales Manager
B13: P2 | C13: Service | D13: Lift OTIF from 63% to 90%: find the SKUs causing short shipments | E13: short-shipped orders drive credit notes and lost customers | F13: 0 | G13: Warehouse Manager

Sheet Customer profitability 90 days
B1: SHELLY
B2: Customer profitability 90 days
B5: name | C5: revenue | D5: gm_pct | E5: orders | F5: avg_order | G5: contribution
B6: City Cafe | C6: 53754.7 | D6: 17.5 | E6: 7 | F6: 7679.2 | G6: 9306.1
B7: Summit Foods | C7: 46043.8 | D7: 11.4 | E7: 5 | F7: 9208.8 | G7: 5181
B8: Valley Cafe | C8: 39395.9 | D8: 14 | E8: 16 | F8: 2462.2 | G8: 5219.9
B9: North Mart | C9: 34405 | D9: 12.8 | E9: 8 | F9: 4300.6 | G9: 4250.2
B10: Valley Foods | C10: 32663.9 | D10: 13.6 | E10: 20 | F10: 1633.2 | G10: 4090.1
B11: Coast Grocers | C11: 32253.3 | D11: 13.8 | E11: 34 | F11: 948.6 | G11: 3835.4
B12: Valley Superette | C12: 31984 | D12: 20.4 | E12: 38 | F12: 841.7 | G12: 5849.8
B13: Metro Foods | C13: 31212.2 | D13: 7.2 | E13: 37 | F13: 843.6 | G13: 1569.4
B14: Metro Cafe | C14: 30704.1 | D14: 10.7 | E14: 26 | F14: 1180.9 | G14: 2822
B15: Harbour Superette | C15: 30483.6 | D15: 18.8 | E15: 26 | F15: 1172.4 | G15: 5267.3
B16: City Foods | C16: 24942.7 | D16: 9.8 | E16: 21 | F16: 1187.7 | G16: 2069.9
B17: North Foods | C17: 23033.3 | D17: 18.7 | E17: 28 | F17: 822.6 | G17: 3792.7
... B45: North Grocers | C45: 1214 | D45: 11.8 | E45: 66 | F45: 18.4 | G45: -1044.2

Sheet Receivables ageing
B1: SHELLY
B2: Receivables ageing
B5: name | C5: current | D5: 1-30 | E5: 31-60 | F5: 60+ | G5: total
B6: North Mart | C6: 14231 | D6: 0 | E6: 4086 | F6: 0 | G6: 18317
B7: Metro Foods | C7: 9849 | D7: 1858 | E7: 2391 | F7: 788 | G7: 14886
B8: Valley Cafe | C8: 10091 | D8: 0 | E8: 3448 | F8: 0 | G8: 13539
B9: Harbour Superette | C9: 11434 | D9: 0 | E9: 0 | F9: 1382 | G9: 12816
B10: Metro Cafe | C10: 11457 | D10: 1315 | E10: 0 | F10: 0 | G10: 12772
B11: North Foods | C11: 9869 | D11: 1008 | E11: 0 | F11: 0 | G11: 10877
B12: Valley Superette | C12: 9284 | D12: 0 | E12: 1280 | F12: 0 | G12: 10564
B13: Coast Grocers | C13: 7106 | D13: 757 | E13: 1211 | F13: 0 | G13: 9074
B14: City Foods | C14: 7916 | D14: 833 | E14: 0 | F14: 0 | G14: 8749
B15: Summit Grocers | C15: 6424 | D15: 1767 | E15: 0 | F15: 0 | G15: 8191
B16: Valley Foods | C16: 8015 | D16: 0 | E16: 0 | F16: 0 | G16: 8015
B17: City Grocers | C17: 6566 | D17: 0 | E17: 0 | F17: 0 | G17: 6566
... B43: North Grocers | C43: 198 | D43: 0 | E43: 53 | F43: 0 | G43: 251

Sheet Fill rate & OTIF
B1: SHELLY
B2: Fill rate & OTIF
B5: fill_rate_pct | C5: otif_pct | D5: orders
B6: 97.8 | C6: 63.2 | D6: 981

Sheet Notes
B1: SHELLY
B2: Notes, method and sign-off
B3: How the numbers were made, what each column means, and who approved it.
B5: About this workbook
C6: Industry pack demo. Replace Raw with your own export (same column names) and the Model, KPIs and pivots follow.
C7: Analysis sheets hold Shelly's skill results; Actions lists findings for your confirmation.
B9: Data dictionary (Raw sheet)
B10: Date
B11: Week
B12: Order
B13: Customer
B14: Revenue
B15: Cost
B16: Gross margin
B18: Sign-off
B19: Findings reviewed | C19: Name: ____________ Date: ________ ☐ Approved ☐ Changes needed
B21: Generated by Shelly on 11 Oct 2026 21:21
