Workbook
Name in_splh: Assumptions!$C$6
Name in_min_hours: Assumptions!$C$7
Name in_wage: Assumptions!$C$8
Name SelCat: Dashboard!$B$6
Name CatCrit: IF(Dashboard!$B$6="All","*",Dashboard!$B$6)

Sheet Dashboard
B1: SHELLY
B2: Roster & labour plan
B3: Demo Neighbourhood Store (Eden Terrace format) · from 12 Oct 2026
B5: Scope (store)
B6: All
B7: Change the blue cell to filter the whole workbook.
B9: HOURS NEXT 7 DAYS | E9: WAGES NEXT 7 DAYS | H9: WAGE % OF SALES | K9: 13-WEEK WAGE BUDGET
B10: =Model!$D$15 -> 188.78818 | E10: =Model!$E$15 -> 5097.2809 | H10: =Model!$F$15 -> 0.25369969 | K10: =Model!$E$34 -> 67683.76
B13: 13-WEEK HOURS | E13: AVERAGE FTE
B14: =Model!$D$34 -> 2506.8059 | E14: =Model!$G$34 -> 4.8207806

Sheet Model
B1: SHELLY
B2: Model
B3: Live formulas over Raw, Lookup and Assumptions. Nothing on this sheet is typed in.
B5: Next 7 days
B7: Date | C7: Forecast sales | D7: Hours | E7: Wages | F7: Wage % | G7: People (8h shifts)
B8: 46307 | C8: =SUMIFS(Raw!$C$2:$C$21,Raw!$B$2:$B$21,"Day",Raw!$A$2:$A$21,$B8) -> 3050.03 | D8: =MAX(Assumptions!$C$7,C8/Assumptions!$C$6) -> 27.727545 | E8: =D8*Assumptions!$C$8 -> 748.64373 | F8: =IFERROR(E8/C8,0) -> 0.24545455 | G8: =ROUNDUP(D8/8,0) -> 4
B9: 46308 | C9: =SUMIFS(Raw!$C$2:$C$21,Raw!$B$2:$B$21,"Day",Raw!$A$2:$A$21,$B9) -> 3029.57 | D9: =MAX(Assumptions!$C$7,C9/Assumptions!$C$6) -> 27.541545 | E9: =D9*Assumptions!$C$8 -> 743.62173 | F9: =IFERROR(E9/C9,0) -> 0.24545455 | G9: =ROUNDUP(D9/8,0) -> 4
B10: 46309 | C10: =SUMIFS(Raw!$C$2:$C$21,Raw!$B$2:$B$21,"Day",Raw!$A$2:$A$21,$B10) -> 2955.89 | D10: =MAX(Assumptions!$C$7,C10/Assumptions!$C$6) -> 26.871727 | E10: =D10*Assumptions!$C$8 -> 725.53664 | F10: =IFERROR(E10/C10,0) -> 0.24545455 | G10: =ROUNDUP(D10/8,0) -> 4
B11: 46310 | C11: =SUMIFS(Raw!$C$2:$C$21,Raw!$B$2:$B$21,"Day",Raw!$A$2:$A$21,$B11) -> 3203.6 | D11: =MAX(Assumptions!$C$7,C11/Assumptions!$C$6) -> 29.123636 | E11: =D11*Assumptions!$C$8 -> 786.33818 | F11: =IFERROR(E11/C11,0) -> 0.24545455 | G11: =ROUNDUP(D11/8,0) -> 4
B12: 46311 | C12: =SUMIFS(Raw!$C$2:$C$21,Raw!$B$2:$B$21,"Day",Raw!$A$2:$A$21,$B12) -> 3247.61 | D12: =MAX(Assumptions!$C$7,C12/Assumptions!$C$6) -> 29.523727 | E12: =D12*Assumptions!$C$8 -> 797.14064 | F12: =IFERROR(E12/C12,0) -> 0.24545455 | G12: =ROUNDUP(D12/8,0) -> 4
B13: 46312 | C13: =SUMIFS(Raw!$C$2:$C$21,Raw!$B$2:$B$21,"Day",Raw!$A$2:$A$21,$B13) -> 2502.67 | D13: =MAX(Assumptions!$C$7,C13/Assumptions!$C$6) -> 24 | E13: =D13*Assumptions!$C$8 -> 648 | F13: =IFERROR(E13/C13,0) -> 0.25892347 | G13: =ROUNDUP(D13/8,0) -> 3
B14: 46313 | C14: =SUMIFS(Raw!$C$2:$C$21,Raw!$B$2:$B$21,"Day",Raw!$A$2:$A$21,$B14) -> 2102.42 | D14: =MAX(Assumptions!$C$7,C14/Assumptions!$C$6) -> 24 | E14: =D14*Assumptions!$C$8 -> 648 | F14: =IFERROR(E14/C14,0) -> 0.30821625 | G14: =ROUNDUP(D14/8,0) -> 3
B15: Total | C15: =SUM(C8:C14) -> 20091.79 | D15: =SUM(D8:D14) -> 188.78818 | E15: =SUM(E8:E14) -> 5097.2809 | F15: =IFERROR(E15/C15,0) -> 0.25369969 | G15: =SUM(G8:G14) -> 26
B18: Next 13 weeks
B20: Week starting | C20: Forecast sales | D20: Hours | E20: Wages | F20: Wage % | G20: FTE (40h)
B21: 46307 | C21: =SUMIFS(Raw!$C$2:$C$21,Raw!$B$2:$B$21,"Week",Raw!$A$2:$A$21,$B21) -> 20091.79 | D21: =MAX(Assumptions!$C$7*7,C21/Assumptions!$C$6) -> 182.65264 | E21: =D21*Assumptions!$C$8 -> 4931.6212 | F21: =IFERROR(E21/C21,0) -> 0.24545455 | G21: =D21/40 -> 4.5663159
B22: 46314 | C22: =SUMIFS(Raw!$C$2:$C$21,Raw!$B$2:$B$21,"Week",Raw!$A$2:$A$21,$B22) -> 20879.38 | D22: =MAX(Assumptions!$C$7*7,C22/Assumptions!$C$6) -> 189.81255 | E22: =D22*Assumptions!$C$8 -> 5124.9387 | F22: =IFERROR(E22/C22,0) -> 0.24545455 | G22: =D22/40 -> 4.7453136
B23: 46321 | C23: =SUMIFS(Raw!$C$2:$C$21,Raw!$B$2:$B$21,"Week",Raw!$A$2:$A$21,$B23) -> 19819.66 | D23: =MAX(Assumptions!$C$7*7,C23/Assumptions!$C$6) -> 180.17873 | E23: =D23*Assumptions!$C$8 -> 4864.8256 | F23: =IFERROR(E23/C23,0) -> 0.24545455 | G23: =D23/40 -> 4.5044682
B24: 46328 | C24: =SUMIFS(Raw!$C$2:$C$21,Raw!$B$2:$B$21,"Week",Raw!$A$2:$A$21,$B24) -> 21739.04 | D24: =MAX(Assumptions!$C$7*7,C24/Assumptions!$C$6) -> 197.62764 | E24: =D24*Assumptions!$C$8 -> 5335.9462 | F24: =IFERROR(E24/C24,0) -> 0.24545455 | G24: =D24/40 -> 4.9406909
B25: 46335 | C25: =SUMIFS(Raw!$C$2:$C$21,Raw!$B$2:$B$21,"Week",Raw!$A$2:$A$21,$B25) -> 20952.55 | D25: =MAX(Assumptions!$C$7*7,C25/Assumptions!$C$6) -> 190.47773 | E25: =D25*Assumptions!$C$8 -> 5142.8986 | F25: =IFERROR(E25/C25,0) -> 0.24545455 | G25: =D25/40 -> 4.7619432
B26: 46342 | C26: =SUMIFS(Raw!$C$2:$C$21,Raw!$B$2:$B$21,"Week",Raw!$A$2:$A$21,$B26) -> 21464.6 | D26: =MAX(Assumptions!$C$7*7,C26/Assumptions!$C$6) -> 195.13273 | E26: =D26*Assumptions!$C$8 -> 5268.5836 | F26: =IFERROR(E26/C26,0) -> 0.24545455 | G26: =D26/40 -> 4.8783182
B27: 46349 | C27: =SUMIFS(Raw!$C$2:$C$21,Raw!$B$2:$B$21,"Week",Raw!$A$2:$A$21,$B27) -> 20629.81 | D27: =MAX(Assumptions!$C$7*7,C27/Assumptions!$C$6) -> 187.54373 | E27: =D27*Assumptions!$C$8 -> 5063.6806 | F27: =IFERROR(E27/C27,0) -> 0.24545455 | G27: =D27/40 -> 4.6885932
B28: 46356 | C28: =SUMIFS(Raw!$C$2:$C$21,Raw!$B$2:$B$21,"Week",Raw!$A$2:$A$21,$B28) -> 23790.29 | D28: =MAX(Assumptions!$C$7*7,C28/Assumptions!$C$6) -> 216.27536 | E28: =D28*Assumptions!$C$8 -> 5839.4348 | F28: =IFERROR(E28/C28,0) -> 0.24545455 | G28: =D28/40 -> 5.4068841
B29: 46363 | C29: =SUMIFS(Raw!$C$2:$C$21,Raw!$B$2:$B$21,"Week",Raw!$A$2:$A$21,$B29) -> 23214.98 | D29: =MAX(Assumptions!$C$7*7,C29/Assumptions!$C$6) -> 211.04527 | E29: =D29*Assumptions!$C$8 -> 5698.2224 | F29: =IFERROR(E29/C29,0) -> 0.24545455 | G29: =D29/40 -> 5.2761318
B30: 46370 | C30: =SUMIFS(Raw!$C$2:$C$21,Raw!$B$2:$B$21,"Week",Raw!$A$2:$A$21,$B30) -> 23268.04 | D30: =MAX(Assumptions!$C$7*7,C30/Assumptions!$C$6) -> 211.52764 | E30: =D30*Assumptions!$C$8 -> 5711.2462 | F30: =IFERROR(E30/C30,0) -> 0.24545455 | G30: =D30/40 -> 5.2881909
B31: 46377 | C31: =SUMIFS(Raw!$C$2:$C$21,Raw!$B$2:$B$21,"Week",Raw!$A$2:$A$21,$B31) -> 20933.69 | D31: =MAX(Assumptions!$C$7*7,C31/Assumptions!$C$6) -> 190.30627 | E31: =D31*Assumptions!$C$8 -> 5138.2694 | F31: =IFERROR(E31/C31,0) -> 0.24545455 | G31: =D31/40 -> 4.7576568
B32: 46384 | C32: =SUMIFS(Raw!$C$2:$C$21,Raw!$B$2:$B$21,"Week",Raw!$A$2:$A$21,$B32) -> 20028.24 | D32: =MAX(Assumptions!$C$7*7,C32/Assumptions!$C$6) -> 182.07491 | E32: =D32*Assumptions!$C$8 -> 4916.0225 | F32: =IFERROR(E32/C32,0) -> 0.24545455 | G32: =D32/40 -> 4.5518727
B33: 46391 | C33: =SUMIFS(Raw!$C$2:$C$21,Raw!$B$2:$B$21,"Week",Raw!$A$2:$A$21,$B33) -> 18936.58 | D33: =MAX(Assumptions!$C$7*7,C33/Assumptions!$C$6) -> 172.15073 | E33: =D33*Assumptions!$C$8 -> 4648.0696 | F33: =IFERROR(E33/C33,0) -> 0.24545455 | G33: =D33/40 -> 4.3037682
B34: Total | C34: =SUM(C21:C33) -> 275748.65 | D34: =SUM(D21:D33) -> 2506.8059 | E34: =SUM(E21:E33) -> 67683.76 | F34: =IFERROR(E34/C34,0) -> 0.24545455 | G34: =IFERROR(AVERAGE(G21:G33),0) -> 4.8207806

Sheet Pivot
B1: SHELLY
B2: Pivot tables
B3: Real Excel PivotTables over the Raw sheet: drag fields in the PivotTable pane to explore. They refresh when the file opens.
A5: Forecast sales by type
A6: Row Labels | B6: Forecast sales
A7: Day | B7: 20091.79
A8: Week | B8: 275748.65
A9: Grand Total | B9: 295840.44

Sheet Raw
A1: Date | B1: Type | C1: Forecast sales
A2: 46307 | B2: Day | C2: 3050.03
A3: 46308 | B3: Day | C3: 3029.57
A4: 46309 | B4: Day | C4: 2955.89
A5: 46310 | B5: Day | C5: 3203.6
A6: 46311 | B6: Day | C6: 3247.61
A7: 46312 | B7: Day | C7: 2502.67
A8: 46313 | B8: Day | C8: 2102.42
A9: 46307 | B9: Week | C9: 20091.79
A10: 46314 | B10: Week | C10: 20879.38
A11: 46321 | B11: Week | C11: 19819.66
A12: 46328 | B12: Week | C12: 21739.04
A13: 46335 | B13: Week | C13: 20952.55
... A21: 46391 | B21: Week | C21: 18936.58

Sheet Lookup
B1: SHELLY
B2: Lookup tables
B3: Reference data used by INDEX-MATCH formulas in the Model sheet.

Sheet Assumptions
B1: SHELLY
B2: Assumptions
B3: Blue cells are inputs: change them and every sheet recalculates.
B5: Input | C5: Value | D5: Why / source
B6: Sales per labour hour target ($) | C6: 110 | D6: Productivity target
B7: Minimum hours per day | C7: 24 | D7: e.g. two people open to close
B8: Average wage rate ($/h) | C8: 27 | D8: Include on-costs if you want the full cost

Sheet Notes
B1: SHELLY
B2: Notes, method and sign-off
B3: How the numbers were made, what each column means, and who approved it.
B5: About this workbook
C6: Store: Demo Neighbourhood Store (Eden Terrace format). Data to 11 Oct 2026. Shelly v1.19.0.
C7: Synthetic demo data.
C8: Change the blue Category cell on the Dashboard, or any blue input on Assumptions: every formula follows.
B10: Method
C11: Hours = forecast sales ÷ sales-per-hour target, never below the minimum.
C12: Change the three blue inputs on Assumptions to test other productivity or wage levels.
B14: Data dictionary (Raw sheet)
B15: Date | C15: Day (Type = Day) or week start (Type = Week)
B16: Forecast sales | C16: Shelly's forecast ($)
B18: Sign-off
B19: Roster approved | C19: Name: ____________ Date: ________ ☐ Approved ☐ Changes needed
B20: Labour budget approved | C20: Name: ____________ Date: ________ ☐ Approved ☐ Changes needed
B22: Generated by Shelly on 11 Oct 2026 21:21
