Workbook
Name in_growth: Assumptions!$C$6
Name in_start: Assumptions!$C$7
Name in_months: Assumptions!$C$8
Name SelCat: Dashboard!$B$6
Name CatCrit: IF(Dashboard!$B$6="All","*",Dashboard!$B$6)

Sheet Dashboard
B1: SHELLY
B2: Budget & forecast plan
B3: Demo Neighbourhood Store (Eden Terrace format) · 12 months from Nov 2026 · data to 11 Oct 2026
B5: Category
B6: All
B7: Change the blue cell to filter the whole workbook.
B9: BUDGET (PLAN WINDOW) | E9: FORECAST | H9: GAP TO BUDGET | K9: GAP %
B10: =SUMIFS(Model!$D$8:$D$19,Model!$L$8:$L$19,1) -> 278886.75 | E10: =SUMIFS(Model!$E$8:$E$19,Model!$L$8:$L$19,1) -> 279339.13 | H10: =SUMIFS(Model!$H$8:$H$19,Model!$L$8:$L$19,1) -> 452.3764 | K10: =IFERROR(SUMIFS(Model!$H$8:$H$19,Model!$L$8:$L$19,1)/SUMIFS(Model!$D$8:$D$19,Model!$L$8:$L$19,1),0) -> 0.0016220792
H11: Forecast − budget
B13: LAST YEAR | E13: BUDGET GM % | H13: FORECAST LOW | K13: FORECAST HIGH
B14: =SUMIFS(Model!$C$8:$C$19,Model!$L$8:$L$19,1) -> 268160.34 | E14: =IFERROR(SUMIFS(Model!$K$8:$K$19,Model!$L$8:$L$19,1)/SUMIFS(Model!$D$8:$D$19,Model!$L$8:$L$19,1),0) -> 0.40769123 | H14: =SUMIFS(Model!$F$8:$F$19,Model!$L$8:$L$19,1) -> 263990.2 | K14: =SUMIFS(Model!$G$8:$G$19,Model!$L$8:$L$19,1) -> 294688.11

Sheet Model
B1: SHELLY
B2: Model
B3: Live formulas over Raw, Lookup and Assumptions. Nothing on this sheet is typed in.
B5: Monthly plan (next 12 months)
B6: Rows inside the plan window (Assumptions: start month + months in plan) are counted in the KPIs.
B7: Month | C7: Last year | D7: Budget | E7: Forecast | F7: Low | G7: High | H7: Gap | I7: Gap % | J7: LY GM | K7: Budget GM | L7: In plan
B8: 46327 | C8: =SUMIFS(Raw!$D$2:$D$397,Raw!$C$2:$C$397,"Actual",Raw!$B$2:$B$397,CatCrit,Raw!$A$2:$A$397,EDATE($B8,-12))+SUMIFS(Raw!$D$2:$D$397,Raw!$C$2:$C$397,"Outlook",Raw!$B$2:$B$397,CatCrit,Raw!$A$2:$A$397,EDATE($B8,-12)) -> 85639.06 | D8: =C8*(1+Assumptions!$C$6) -> 89064.622 | E8: =SUMIFS(Raw!$D$2:$D$397,Raw!$C$2:$C$397,"Forecast",Raw!$B$2:$B$397,CatCrit,Raw!$A$2:$A$397,$B8) -> 89230.15 | F8: =SUMIFS(Raw!$G$2:$G$397,Raw!$C$2:$C$397,"Forecast",Raw!$B$2:$B$397,CatCrit,Raw!$A$2:$A$397,$B8) -> 84327.18 | G8: =SUMIFS(Raw!$H$2:$H$397,Raw!$C$2:$C$397,"Forecast",Raw!$B$2:$B$397,CatCrit,Raw!$A$2:$A$397,$B8) -> 94133.12 | H8: =E8-D8 -> 165.5276 | I8: =IFERROR(H8/D8,0) -> 0.0018585112 | J8: =SUMIFS(Raw!$E$2:$E$397,Raw!$C$2:$C$397,"Actual",Raw!$B$2:$B$397,CatCrit,Raw!$A$2:$A$397,EDATE($B8,-12))+SUMIFS(Raw!$E$2:$E$397,Raw!$C$2:$C$397,"Outlook",Raw!$B$2:$B$397,CatCrit,Raw!$A$2:$A$397,EDATE($B8,-12)) -> 34921.57 | K8: =IFERROR(D8*J8/C8,0) -> 36318.433 | L8: =IF(AND($B8>=Assumptions!$C$7,$B8<=EDATE(Assumptions!$C$7,Assumptions!$C$8-1)),1,0) -> 1
B9: 46357 | C9: =SUMIFS(Raw!$D$2:$D$397,Raw!$C$2:$C$397,"Actual",Raw!$B$2:$B$397,CatCrit,Raw!$A$2:$A$397,EDATE($B9,-12))+SUMIFS(Raw!$D$2:$D$397,Raw!$C$2:$C$397,"Outlook",Raw!$B$2:$B$397,CatCrit,Raw!$A$2:$A$397,EDATE($B9,-12)) -> 98239.77 | D9: =C9*(1+Assumptions!$C$6) -> 102169.36 | E9: =SUMIFS(Raw!$D$2:$D$397,Raw!$C$2:$C$397,"Forecast",Raw!$B$2:$B$397,CatCrit,Raw!$A$2:$A$397,$B9) -> 102308.92 | F9: =SUMIFS(Raw!$G$2:$G$397,Raw!$C$2:$C$397,"Forecast",Raw!$B$2:$B$397,CatCrit,Raw!$A$2:$A$397,$B9) -> 96687.32 | G9: =SUMIFS(Raw!$H$2:$H$397,Raw!$C$2:$C$397,"Forecast",Raw!$B$2:$B$397,CatCrit,Raw!$A$2:$A$397,$B9) -> 107930.53 | H9: =E9-D9 -> 139.5592 | I9: =IFERROR(H9/D9,0) -> 0.0013659594 | J9: =SUMIFS(Raw!$E$2:$E$397,Raw!$C$2:$C$397,"Actual",Raw!$B$2:$B$397,CatCrit,Raw!$A$2:$A$397,EDATE($B9,-12))+SUMIFS(Raw!$E$2:$E$397,Raw!$C$2:$C$397,"Outlook",Raw!$B$2:$B$397,CatCrit,Raw!$A$2:$A$397,EDATE($B9,-12)) -> 40021.79 | K9: =IFERROR(D9*J9/C9,0) -> 41622.662 | L9: =IF(AND($B9>=Assumptions!$C$7,$B9<=EDATE(Assumptions!$C$7,Assumptions!$C$8-1)),1,0) -> 1
B10: 46388 | C10: =SUMIFS(Raw!$D$2:$D$397,Raw!$C$2:$C$397,"Actual",Raw!$B$2:$B$397,CatCrit,Raw!$A$2:$A$397,EDATE($B10,-12))+SUMIFS(Raw!$D$2:$D$397,Raw!$C$2:$C$397,"Outlook",Raw!$B$2:$B$397,CatCrit,Raw!$A$2:$A$397,EDATE($B10,-12)) -> 84281.51 | D10: =C10*(1+Assumptions!$C$6) -> 87652.77 | E10: =SUMIFS(Raw!$D$2:$D$397,Raw!$C$2:$C$397,"Forecast",Raw!$B$2:$B$397,CatCrit,Raw!$A$2:$A$397,$B10) -> 87800.06 | F10: =SUMIFS(Raw!$G$2:$G$397,Raw!$C$2:$C$397,"Forecast",Raw!$B$2:$B$397,CatCrit,Raw!$A$2:$A$397,$B10) -> 82975.7 | G10: =SUMIFS(Raw!$H$2:$H$397,Raw!$C$2:$C$397,"Forecast",Raw!$B$2:$B$397,CatCrit,Raw!$A$2:$A$397,$B10) -> 92624.46 | H10: =E10-D10 -> 147.2896 | I10: =IFERROR(H10/D10,0) -> 0.0016803759 | J10: =SUMIFS(Raw!$E$2:$E$397,Raw!$C$2:$C$397,"Actual",Raw!$B$2:$B$397,CatCrit,Raw!$A$2:$A$397,EDATE($B10,-12))+SUMIFS(Raw!$E$2:$E$397,Raw!$C$2:$C$397,"Outlook",Raw!$B$2:$B$397,CatCrit,Raw!$A$2:$A$397,EDATE($B10,-12)) -> 34383.26 | K10: =IFERROR(D10*J10/C10,0) -> 35758.59 | L10: =IF(AND($B10>=Assumptions!$C$7,$B10<=EDATE(Assumptions!$C$7,Assumptions!$C$8-1)),1,0) -> 1
B11: 46419 | C11: =SUMIFS(Raw!$D$2:$D$397,Raw!$C$2:$C$397,"Actual",Raw!$B$2:$B$397,CatCrit,Raw!$A$2:$A$397,EDATE($B11,-12))+SUMIFS(Raw!$D$2:$D$397,Raw!$C$2:$C$397,"Outlook",Raw!$B$2:$B$397,CatCrit,Raw!$A$2:$A$397,EDATE($B11,-12)) -> 84064.41 | D11: =C11*(1+Assumptions!$C$6) -> 87426.986 | E11: =SUMIFS(Raw!$D$2:$D$397,Raw!$C$2:$C$397,"Forecast",Raw!$B$2:$B$397,CatCrit,Raw!$A$2:$A$397,$B11) -> 87569.26 | F11: =SUMIFS(Raw!$G$2:$G$397,Raw!$C$2:$C$397,"Forecast",Raw!$B$2:$B$397,CatCrit,Raw!$A$2:$A$397,$B11) -> 82757.55 | G11: =SUMIFS(Raw!$H$2:$H$397,Raw!$C$2:$C$397,"Forecast",Raw!$B$2:$B$397,CatCrit,Raw!$A$2:$A$397,$B11) -> 92380.96 | H11: =E11-D11 -> 142.2736 | I11: =IFERROR(H11/D11,0) -> 0.0016273419 | J11: =SUMIFS(Raw!$E$2:$E$397,Raw!$C$2:$C$397,"Actual",Raw!$B$2:$B$397,CatCrit,Raw!$A$2:$A$397,EDATE($B11,-12))+SUMIFS(Raw!$E$2:$E$397,Raw!$C$2:$C$397,"Outlook",Raw!$B$2:$B$397,CatCrit,Raw!$A$2:$A$397,EDATE($B11,-12)) -> 34264.11 | K11: =IFERROR(D11*J11/C11,0) -> 35634.674 | L11: =IF(AND($B11>=Assumptions!$C$7,$B11<=EDATE(Assumptions!$C$7,Assumptions!$C$8-1)),1,0) -> 0
B12: 46447 | C12: =SUMIFS(Raw!$D$2:$D$397,Raw!$C$2:$C$397,"Actual",Raw!$B$2:$B$397,CatCrit,Raw!$A$2:$A$397,EDATE($B12,-12))+SUMIFS(Raw!$D$2:$D$397,Raw!$C$2:$C$397,"Outlook",Raw!$B$2:$B$397,CatCrit,Raw!$A$2:$A$397,EDATE($B12,-12)) -> 89855.75 | D12: =C12*(1+Assumptions!$C$6) -> 93449.98 | E12: =SUMIFS(Raw!$D$2:$D$397,Raw!$C$2:$C$397,"Forecast",Raw!$B$2:$B$397,CatCrit,Raw!$A$2:$A$397,$B12) -> 93625.46 | F12: =SUMIFS(Raw!$G$2:$G$397,Raw!$C$2:$C$397,"Forecast",Raw!$B$2:$B$397,CatCrit,Raw!$A$2:$A$397,$B12) -> 88480.98 | G12: =SUMIFS(Raw!$H$2:$H$397,Raw!$C$2:$C$397,"Forecast",Raw!$B$2:$B$397,CatCrit,Raw!$A$2:$A$397,$B12) -> 98769.91 | H12: =E12-D12 -> 175.48 | I12: =IFERROR(H12/D12,0) -> 0.001877796 | J12: =SUMIFS(Raw!$E$2:$E$397,Raw!$C$2:$C$397,"Actual",Raw!$B$2:$B$397,CatCrit,Raw!$A$2:$A$397,EDATE($B12,-12))+SUMIFS(Raw!$E$2:$E$397,Raw!$C$2:$C$397,"Outlook",Raw!$B$2:$B$397,CatCrit,Raw!$A$2:$A$397,EDATE($B12,-12)) -> 36945.21 | K12: =IFERROR(D12*J12/C12,0) -> 38423.018 | L12: =IF(AND($B12>=Assumptions!$C$7,$B12<=EDATE(Assumptions!$C$7,Assumptions!$C$8-1)),1,0) -> 0
B13: 46478 | C13: =SUMIFS(Raw!$D$2:$D$397,Raw!$C$2:$C$397,"Actual",Raw!$B$2:$B$397,CatCrit,Raw!$A$2:$A$397,EDATE($B13,-12))+SUMIFS(Raw!$D$2:$D$397,Raw!$C$2:$C$397,"Outlook",Raw!$B$2:$B$397,CatCrit,Raw!$A$2:$A$397,EDATE($B13,-12)) -> 82882.76 | D13: =C13*(1+Assumptions!$C$6) -> 86198.07 | E13: =SUMIFS(Raw!$D$2:$D$397,Raw!$C$2:$C$397,"Forecast",Raw!$B$2:$B$397,CatCrit,Raw!$A$2:$A$397,$B13) -> 86402.49 | F13: =SUMIFS(Raw!$G$2:$G$397,Raw!$C$2:$C$397,"Forecast",Raw!$B$2:$B$397,CatCrit,Raw!$A$2:$A$397,$B13) -> 81654.9 | G13: =SUMIFS(Raw!$H$2:$H$397,Raw!$C$2:$C$397,"Forecast",Raw!$B$2:$B$397,CatCrit,Raw!$A$2:$A$397,$B13) -> 91150.07 | H13: =E13-D13 -> 204.4196 | I13: =IFERROR(H13/D13,0) -> 0.0023715102 | J13: =SUMIFS(Raw!$E$2:$E$397,Raw!$C$2:$C$397,"Actual",Raw!$B$2:$B$397,CatCrit,Raw!$A$2:$A$397,EDATE($B13,-12))+SUMIFS(Raw!$E$2:$E$397,Raw!$C$2:$C$397,"Outlook",Raw!$B$2:$B$397,CatCrit,Raw!$A$2:$A$397,EDATE($B13,-12)) -> 33376.32 | K13: =IFERROR(D13*J13/C13,0) -> 34711.373 | L13: =IF(AND($B13>=Assumptions!$C$7,$B13<=EDATE(Assumptions!$C$7,Assumptions!$C$8-1)),1,0) -> 0
B14: 46508 | C14: =SUMIFS(Raw!$D$2:$D$397,Raw!$C$2:$C$397,"Actual",Raw!$B$2:$B$397,CatCrit,Raw!$A$2:$A$397,EDATE($B14,-12))+SUMIFS(Raw!$D$2:$D$397,Raw!$C$2:$C$397,"Outlook",Raw!$B$2:$B$397,CatCrit,Raw!$A$2:$A$397,EDATE($B14,-12)) -> 84779.09 | D14: =C14*(1+Assumptions!$C$6) -> 88170.254 | E14: =SUMIFS(Raw!$D$2:$D$397,Raw!$C$2:$C$397,"Forecast",Raw!$B$2:$B$397,CatCrit,Raw!$A$2:$A$397,$B14) -> 88339.85 | F14: =SUMIFS(Raw!$G$2:$G$397,Raw!$C$2:$C$397,"Forecast",Raw!$B$2:$B$397,CatCrit,Raw!$A$2:$A$397,$B14) -> 83485.82 | G14: =SUMIFS(Raw!$H$2:$H$397,Raw!$C$2:$C$397,"Forecast",Raw!$B$2:$B$397,CatCrit,Raw!$A$2:$A$397,$B14) -> 93193.92 | H14: =E14-D14 -> 169.5964 | I14: =IFERROR(H14/D14,0) -> 0.0019235104 | J14: =SUMIFS(Raw!$E$2:$E$397,Raw!$C$2:$C$397,"Actual",Raw!$B$2:$B$397,CatCrit,Raw!$A$2:$A$397,EDATE($B14,-12))+SUMIFS(Raw!$E$2:$E$397,Raw!$C$2:$C$397,"Outlook",Raw!$B$2:$B$397,CatCrit,Raw!$A$2:$A$397,EDATE($B14,-12)) -> 34208.29 | K14: =IFERROR(D14*J14/C14,0) -> 35576.622 | L14: =IF(AND($B14>=Assumptions!$C$7,$B14<=EDATE(Assumptions!$C$7,Assumptions!$C$8-1)),1,0) -> 0
B15: 46539 | C15: =SUMIFS(Raw!$D$2:$D$397,Raw!$C$2:$C$397,"Actual",Raw!$B$2:$B$397,CatCrit,Raw!$A$2:$A$397,EDATE($B15,-12))+SUMIFS(Raw!$D$2:$D$397,Raw!$C$2:$C$397,"Outlook",Raw!$B$2:$B$397,CatCrit,Raw!$A$2:$A$397,EDATE($B15,-12)) -> 79827.04 | D15: =C15*(1+Assumptions!$C$6) -> 83020.122 | E15: =SUMIFS(Raw!$D$2:$D$397,Raw!$C$2:$C$397,"Forecast",Raw!$B$2:$B$397,CatCrit,Raw!$A$2:$A$397,$B15) -> 83192.69 | F15: =SUMIFS(Raw!$G$2:$G$397,Raw!$C$2:$C$397,"Forecast",Raw!$B$2:$B$397,CatCrit,Raw!$A$2:$A$397,$B15) -> 78621.46 | G15: =SUMIFS(Raw!$H$2:$H$397,Raw!$C$2:$C$397,"Forecast",Raw!$B$2:$B$397,CatCrit,Raw!$A$2:$A$397,$B15) -> 87763.9 | H15: =E15-D15 -> 172.5684 | I15: =IFERROR(H15/D15,0) -> 0.0020786334 | J15: =SUMIFS(Raw!$E$2:$E$397,Raw!$C$2:$C$397,"Actual",Raw!$B$2:$B$397,CatCrit,Raw!$A$2:$A$397,EDATE($B15,-12))+SUMIFS(Raw!$E$2:$E$397,Raw!$C$2:$C$397,"Outlook",Raw!$B$2:$B$397,CatCrit,Raw!$A$2:$A$397,EDATE($B15,-12)) -> 32458.29 | K15: =IFERROR(D15*J15/C15,0) -> 33756.622 | L15: =IF(AND($B15>=Assumptions!$C$7,$B15<=EDATE(Assumptions!$C$7,Assumptions!$C$8-1)),1,0) -> 0
B16: 46569 | C16: =SUMIFS(Raw!$D$2:$D$397,Raw!$C$2:$C$397,"Actual",Raw!$B$2:$B$397,CatCrit,Raw!$A$2:$A$397,EDATE($B16,-12))+SUMIFS(Raw!$D$2:$D$397,Raw!$C$2:$C$397,"Outlook",Raw!$B$2:$B$397,CatCrit,Raw!$A$2:$A$397,EDATE($B16,-12)) -> 82245.99 | D16: =C16*(1+Assumptions!$C$6) -> 85535.83 | E16: =SUMIFS(Raw!$D$2:$D$397,Raw!$C$2:$C$397,"Forecast",Raw!$B$2:$B$397,CatCrit,Raw!$A$2:$A$397,$B16) -> 85731.56 | F16: =SUMIFS(Raw!$G$2:$G$397,Raw!$C$2:$C$397,"Forecast",Raw!$B$2:$B$397,CatCrit,Raw!$A$2:$A$397,$B16) -> 81020.83 | G16: =SUMIFS(Raw!$H$2:$H$397,Raw!$C$2:$C$397,"Forecast",Raw!$B$2:$B$397,CatCrit,Raw!$A$2:$A$397,$B16) -> 90442.28 | H16: =E16-D16 -> 195.7304 | I16: =IFERROR(H16/D16,0) -> 0.0022882855 | J16: =SUMIFS(Raw!$E$2:$E$397,Raw!$C$2:$C$397,"Actual",Raw!$B$2:$B$397,CatCrit,Raw!$A$2:$A$397,EDATE($B16,-12))+SUMIFS(Raw!$E$2:$E$397,Raw!$C$2:$C$397,"Outlook",Raw!$B$2:$B$397,CatCrit,Raw!$A$2:$A$397,EDATE($B16,-12)) -> 33443.52 | K16: =IFERROR(D16*J16/C16,0) -> 34781.261 | L16: =IF(AND($B16>=Assumptions!$C$7,$B16<=EDATE(Assumptions!$C$7,Assumptions!$C$8-1)),1,0) -> 0
B17: 46600 | C17: =SUMIFS(Raw!$D$2:$D$397,Raw!$C$2:$C$397,"Actual",Raw!$B$2:$B$397,CatCrit,Raw!$A$2:$A$397,EDATE($B17,-12))+SUMIFS(Raw!$D$2:$D$397,Raw!$C$2:$C$397,"Outlook",Raw!$B$2:$B$397,CatCrit,Raw!$A$2:$A$397,EDATE($B17,-12)) -> 83007.22 | D17: =C17*(1+Assumptions!$C$6) -> 86327.509 | E17: =SUMIFS(Raw!$D$2:$D$397,Raw!$C$2:$C$397,"Forecast",Raw!$B$2:$B$397,CatCrit,Raw!$A$2:$A$397,$B17) -> 86514.27 | F17: =SUMIFS(Raw!$G$2:$G$397,Raw!$C$2:$C$397,"Forecast",Raw!$B$2:$B$397,CatCrit,Raw!$A$2:$A$397,$B17) -> 81760.51 | G17: =SUMIFS(Raw!$H$2:$H$397,Raw!$C$2:$C$397,"Forecast",Raw!$B$2:$B$397,CatCrit,Raw!$A$2:$A$397,$B17) -> 91267.99 | H17: =E17-D17 -> 186.7612 | I17: =IFERROR(H17/D17,0) -> 0.0021634031 | J17: =SUMIFS(Raw!$E$2:$E$397,Raw!$C$2:$C$397,"Actual",Raw!$B$2:$B$397,CatCrit,Raw!$A$2:$A$397,EDATE($B17,-12))+SUMIFS(Raw!$E$2:$E$397,Raw!$C$2:$C$397,"Outlook",Raw!$B$2:$B$397,CatCrit,Raw!$A$2:$A$397,EDATE($B17,-12)) -> 33781.04 | K17: =IFERROR(D17*J17/C17,0) -> 35132.282 | L17: =IF(AND($B17>=Assumptions!$C$7,$B17<=EDATE(Assumptions!$C$7,Assumptions!$C$8-1)),1,0) -> 0
B18: 46631 | C18: =SUMIFS(Raw!$D$2:$D$397,Raw!$C$2:$C$397,"Actual",Raw!$B$2:$B$397,CatCrit,Raw!$A$2:$A$397,EDATE($B18,-12))+SUMIFS(Raw!$D$2:$D$397,Raw!$C$2:$C$397,"Outlook",Raw!$B$2:$B$397,CatCrit,Raw!$A$2:$A$397,EDATE($B18,-12)) -> 84203.07 | D18: =C18*(1+Assumptions!$C$6) -> 87571.193 | E18: =SUMIFS(Raw!$D$2:$D$397,Raw!$C$2:$C$397,"Forecast",Raw!$B$2:$B$397,CatCrit,Raw!$A$2:$A$397,$B18) -> 87778.81 | F18: =SUMIFS(Raw!$G$2:$G$397,Raw!$C$2:$C$397,"Forecast",Raw!$B$2:$B$397,CatCrit,Raw!$A$2:$A$397,$B18) -> 82955.61 | G18: =SUMIFS(Raw!$H$2:$H$397,Raw!$C$2:$C$397,"Forecast",Raw!$B$2:$B$397,CatCrit,Raw!$A$2:$A$397,$B18) -> 92602.04 | H18: =E18-D18 -> 207.6172 | I18: =IFERROR(H18/D18,0) -> 0.002370839 | J18: =SUMIFS(Raw!$E$2:$E$397,Raw!$C$2:$C$397,"Actual",Raw!$B$2:$B$397,CatCrit,Raw!$A$2:$A$397,EDATE($B18,-12))+SUMIFS(Raw!$E$2:$E$397,Raw!$C$2:$C$397,"Outlook",Raw!$B$2:$B$397,CatCrit,Raw!$A$2:$A$397,EDATE($B18,-12)) -> 34137.11 | K18: =IFERROR(D18*J18/C18,0) -> 35502.594 | L18: =IF(AND($B18>=Assumptions!$C$7,$B18<=EDATE(Assumptions!$C$7,Assumptions!$C$8-1)),1,0) -> 0
B19: 46661 | C19: =SUMIFS(Raw!$D$2:$D$397,Raw!$C$2:$C$397,"Actual",Raw!$B$2:$B$397,CatCrit,Raw!$A$2:$A$397,EDATE($B19,-12))+SUMIFS(Raw!$D$2:$D$397,Raw!$C$2:$C$397,"Outlook",Raw!$B$2:$B$397,CatCrit,Raw!$A$2:$A$397,EDATE($B19,-12)) -> 88042.66 | D19: =C19*(1+Assumptions!$C$6) -> 91564.366 | E19: =SUMIFS(Raw!$D$2:$D$397,Raw!$C$2:$C$397,"Forecast",Raw!$B$2:$B$397,CatCrit,Raw!$A$2:$A$397,$B19) -> 91783.62 | F19: =SUMIFS(Raw!$G$2:$G$397,Raw!$C$2:$C$397,"Forecast",Raw!$B$2:$B$397,CatCrit,Raw!$A$2:$A$397,$B19) -> 86740.34 | G19: =SUMIFS(Raw!$H$2:$H$397,Raw!$C$2:$C$397,"Forecast",Raw!$B$2:$B$397,CatCrit,Raw!$A$2:$A$397,$B19) -> 96826.89 | H19: =E19-D19 -> 219.2536 | I19: =IFERROR(H19/D19,0) -> 0.0023945298 | J19: =SUMIFS(Raw!$E$2:$E$397,Raw!$C$2:$C$397,"Actual",Raw!$B$2:$B$397,CatCrit,Raw!$A$2:$A$397,EDATE($B19,-12))+SUMIFS(Raw!$E$2:$E$397,Raw!$C$2:$C$397,"Outlook",Raw!$B$2:$B$397,CatCrit,Raw!$A$2:$A$397,EDATE($B19,-12)) -> 35881.98 | K19: =IFERROR(D19*J19/C19,0) -> 37317.259 | L19: =IF(AND($B19>=Assumptions!$C$7,$B19<=EDATE(Assumptions!$C$7,Assumptions!$C$8-1)),1,0) -> 0
B20: Total | C20: =SUM(C8:C19) -> 1027068.3 | D20: =SUM(D8:D19) -> 1068151.1 | E20: =SUM(E8:E19) -> 1070277.1 | F20: =SUM(F8:F19) -> 1011468.2 | G20: =SUM(G8:G19) -> 1129086.1 | H20: =SUM(H8:H19) -> 2126.0768 | I20: =IFERROR(H20/D20,0) -> 0.0019904271 | J20: =SUM(J8:J19) -> 417822.49 | K20: =SUM(K8:K19) -> 434535.39 | L20: =SUM(L8:L19) -> 3
B23: Category plan (plan window)
B24: Every category for the plan window, whatever the Category selector says. Targets and owners come from Lookup via INDEX-MATCH.
B25: Category | C25: Last year | D25: Budget | E25: Forecast | F25: Gap | G25: Gap % | H25: LY GM % | I25: GM target | J25: Owner
B26: Bakery | C26: =SUMIFS(Raw!$D$2:$D$397,Raw!$C$2:$C$397,"Actual",Raw!$B$2:$B$397,$B26,Raw!$A$2:$A$397,">="&EDATE(Assumptions!$C$7,-12),Raw!$A$2:$A$397,"<="&EDATE(Assumptions!$C$7,Assumptions!$C$8-13))+SUMIFS(Raw!$D$2:$D$397,Raw!$C$2:$C$397,"Outlook",Raw!$B$2:$B$397,$B26,Raw!$A$2:$A$397,">="&EDATE(Assumptions!$C$7,-12),Raw!$A$2:$A$397,"<="&EDATE(Assumptions!$C$7,Assumptions!$C$8-13)) -> 14394.92 | D26: =C26*(1+Assumptions!$C$6) -> 14970.717 | E26: =SUMIFS(Raw!$D$2:$D$397,Raw!$C$2:$C$397,"Forecast",Raw!$B$2:$B$397,$B26,Raw!$A$2:$A$397,">="&Assumptions!$C$7,Raw!$A$2:$A$397,"<="&EDATE(Assumptions!$C$7,Assumptions!$C$8-1)) -> 14773.67 | F26: =E26-D26 -> -197.0468 | G26: =IFERROR(F26/D26,0) -> -0.013162149 | H26: =IFERROR((SUMIFS(Raw!$E$2:$E$397,Raw!$C$2:$C$397,"Actual",Raw!$B$2:$B$397,$B26,Raw!$A$2:$A$397,">="&EDATE(Assumptions!$C$7,-12),Raw!$A$2:$A$397,"<="&EDATE(Assumptions!$C$7,Assumptions!$C$8-13))+SUMIFS(Raw!$E$2:$E$397,Raw!$C$2:$C$397,"Outlook",Raw!$B$2:$B$397,$B26,Raw!$A$2:$A$397,">="&EDATE(Assumptions!$C$7,-12),Raw!$A$2:$A$397,"<="&EDATE(Assumptions!$C$7,Assumptions!$C$8-13)))/C26,0) -> 0.38137899 | I26: =IFERROR(INDEX(Lookup!$C$7:$C$17,MATCH($B26,Lookup!$B$7:$B$17,0)),0) -> 0.382 | J26: =IFERROR(INDEX(Lookup!$D$7:$D$17,MATCH($B26,Lookup!$B$7:$B$17,0)),"") -> Store Manager
B27: Beer & Wine | C27: =SUMIFS(Raw!$D$2:$D$397,Raw!$C$2:$C$397,"Actual",Raw!$B$2:$B$397,$B27,Raw!$A$2:$A$397,">="&EDATE(Assumptions!$C$7,-12),Raw!$A$2:$A$397,"<="&EDATE(Assumptions!$C$7,Assumptions!$C$8-13))+SUMIFS(Raw!$D$2:$D$397,Raw!$C$2:$C$397,"Outlook",Raw!$B$2:$B$397,$B27,Raw!$A$2:$A$397,">="&EDATE(Assumptions!$C$7,-12),Raw!$A$2:$A$397,"<="&EDATE(Assumptions!$C$7,Assumptions!$C$8-13)) -> 35682.61 | D27: =C27*(1+Assumptions!$C$6) -> 37109.914 | E27: =SUMIFS(Raw!$D$2:$D$397,Raw!$C$2:$C$397,"Forecast",Raw!$B$2:$B$397,$B27,Raw!$A$2:$A$397,">="&Assumptions!$C$7,Raw!$A$2:$A$397,"<="&EDATE(Assumptions!$C$7,Assumptions!$C$8-1)) -> 35836.91 | F27: =E27-D27 -> -1273.0044 | G27: =IFERROR(F27/D27,0) -> -0.03430362 | H27: =IFERROR((SUMIFS(Raw!$E$2:$E$397,Raw!$C$2:$C$397,"Actual",Raw!$B$2:$B$397,$B27,Raw!$A$2:$A$397,">="&EDATE(Assumptions!$C$7,-12),Raw!$A$2:$A$397,"<="&EDATE(Assumptions!$C$7,Assumptions!$C$8-13))+SUMIFS(Raw!$E$2:$E$397,Raw!$C$2:$C$397,"Outlook",Raw!$B$2:$B$397,$B27,Raw!$A$2:$A$397,">="&EDATE(Assumptions!$C$7,-12),Raw!$A$2:$A$397,"<="&EDATE(Assumptions!$C$7,Assumptions!$C$8-13)))/C27,0) -> 0.3378203 | I27: =IFERROR(INDEX(Lookup!$C$7:$C$17,MATCH($B27,Lookup!$B$7:$B$17,0)),0) -> 0.338 | J27: =IFERROR(INDEX(Lookup!$D$7:$D$17,MATCH($B27,Lookup!$B$7:$B$17,0)),"") -> Licence Manager
B28: Beverages | C28: =SUMIFS(Raw!$D$2:$D$397,Raw!$C$2:$C$397,"Actual",Raw!$B$2:$B$397,$B28,Raw!$A$2:$A$397,">="&EDATE(Assumptions!$C$7,-12),Raw!$A$2:$A$397,"<="&EDATE(Assumptions!$C$7,Assumptions!$C$8-13))+SUMIFS(Raw!$D$2:$D$397,Raw!$C$2:$C$397,"Outlook",Raw!$B$2:$B$397,$B28,Raw!$A$2:$A$397,">="&EDATE(Assumptions!$C$7,-12),Raw!$A$2:$A$397,"<="&EDATE(Assumptions!$C$7,Assumptions!$C$8-13)) -> 45348.71 | D28: =C28*(1+Assumptions!$C$6) -> 47162.658 | E28: =SUMIFS(Raw!$D$2:$D$397,Raw!$C$2:$C$397,"Forecast",Raw!$B$2:$B$397,$B28,Raw!$A$2:$A$397,">="&Assumptions!$C$7,Raw!$A$2:$A$397,"<="&EDATE(Assumptions!$C$7,Assumptions!$C$8-1)) -> 48085.78 | F28: =E28-D28 -> 923.1216 | G28: =IFERROR(F28/D28,0) -> 0.019573146 | H28: =IFERROR((SUMIFS(Raw!$E$2:$E$397,Raw!$C$2:$C$397,"Actual",Raw!$B$2:$B$397,$B28,Raw!$A$2:$A$397,">="&EDATE(Assumptions!$C$7,-12),Raw!$A$2:$A$397,"<="&EDATE(Assumptions!$C$7,Assumptions!$C$8-13))+SUMIFS(Raw!$E$2:$E$397,Raw!$C$2:$C$397,"Outlook",Raw!$B$2:$B$397,$B28,Raw!$A$2:$A$397,">="&EDATE(Assumptions!$C$7,-12),Raw!$A$2:$A$397,"<="&EDATE(Assumptions!$C$7,Assumptions!$C$8-13)))/C28,0) -> 0.50870598 | I28: =IFERROR(INDEX(Lookup!$C$7:$C$17,MATCH($B28,Lookup!$B$7:$B$17,0)),0) -> 0.51 | J28: =IFERROR(INDEX(Lookup!$D$7:$D$17,MATCH($B28,Lookup!$B$7:$B$17,0)),"") -> Duty Manager
B29: Dairy | C29: =SUMIFS(Raw!$D$2:$D$397,Raw!$C$2:$C$397,"Actual",Raw!$B$2:$B$397,$B29,Raw!$A$2:$A$397,">="&EDATE(Assumptions!$C$7,-12),Raw!$A$2:$A$397,"<="&EDATE(Assumptions!$C$7,Assumptions!$C$8-13))+SUMIFS(Raw!$D$2:$D$397,Raw!$C$2:$C$397,"Outlook",Raw!$B$2:$B$397,$B29,Raw!$A$2:$A$397,">="&EDATE(Assumptions!$C$7,-12),Raw!$A$2:$A$397,"<="&EDATE(Assumptions!$C$7,Assumptions!$C$8-13)) -> 41886.63 | D29: =C29*(1+Assumptions!$C$6) -> 43562.095 | E29: =SUMIFS(Raw!$D$2:$D$397,Raw!$C$2:$C$397,"Forecast",Raw!$B$2:$B$397,$B29,Raw!$A$2:$A$397,">="&Assumptions!$C$7,Raw!$A$2:$A$397,"<="&EDATE(Assumptions!$C$7,Assumptions!$C$8-1)) -> 43472.2 | F29: =E29-D29 -> -89.8952 | G29: =IFERROR(F29/D29,0) -> -0.0020636106 | H29: =IFERROR((SUMIFS(Raw!$E$2:$E$397,Raw!$C$2:$C$397,"Actual",Raw!$B$2:$B$397,$B29,Raw!$A$2:$A$397,">="&EDATE(Assumptions!$C$7,-12),Raw!$A$2:$A$397,"<="&EDATE(Assumptions!$C$7,Assumptions!$C$8-13))+SUMIFS(Raw!$E$2:$E$397,Raw!$C$2:$C$397,"Outlook",Raw!$B$2:$B$397,$B29,Raw!$A$2:$A$397,">="&EDATE(Assumptions!$C$7,-12),Raw!$A$2:$A$397,"<="&EDATE(Assumptions!$C$7,Assumptions!$C$8-13)))/C29,0) -> 0.28176007 | I29: =IFERROR(INDEX(Lookup!$C$7:$C$17,MATCH($B29,Lookup!$B$7:$B$17,0)),0) -> 0.278 | J29: =IFERROR(INDEX(Lookup!$D$7:$D$17,MATCH($B29,Lookup!$B$7:$B$17,0)),"") -> Duty Manager
B30: Food To Go | C30: =SUMIFS(Raw!$D$2:$D$397,Raw!$C$2:$C$397,"Actual",Raw!$B$2:$B$397,$B30,Raw!$A$2:$A$397,">="&EDATE(Assumptions!$C$7,-12),Raw!$A$2:$A$397,"<="&EDATE(Assumptions!$C$7,Assumptions!$C$8-13))+SUMIFS(Raw!$D$2:$D$397,Raw!$C$2:$C$397,"Outlook",Raw!$B$2:$B$397,$B30,Raw!$A$2:$A$397,">="&EDATE(Assumptions!$C$7,-12),Raw!$A$2:$A$397,"<="&EDATE(Assumptions!$C$7,Assumptions!$C$8-13)) -> 48378.56 | D30: =C30*(1+Assumptions!$C$6) -> 50313.702 | E30: =SUMIFS(Raw!$D$2:$D$397,Raw!$C$2:$C$397,"Forecast",Raw!$B$2:$B$397,$B30,Raw!$A$2:$A$397,">="&Assumptions!$C$7,Raw!$A$2:$A$397,"<="&EDATE(Assumptions!$C$7,Assumptions!$C$8-1)) -> 49418.77 | F30: =E30-D30 -> -894.9324 | G30: =IFERROR(F30/D30,0) -> -0.017787051 | H30: =IFERROR((SUMIFS(Raw!$E$2:$E$397,Raw!$C$2:$C$397,"Actual",Raw!$B$2:$B$397,$B30,Raw!$A$2:$A$397,">="&EDATE(Assumptions!$C$7,-12),Raw!$A$2:$A$397,"<="&EDATE(Assumptions!$C$7,Assumptions!$C$8-13))+SUMIFS(Raw!$E$2:$E$397,Raw!$C$2:$C$397,"Outlook",Raw!$B$2:$B$397,$B30,Raw!$A$2:$A$397,">="&EDATE(Assumptions!$C$7,-12),Raw!$A$2:$A$397,"<="&EDATE(Assumptions!$C$7,Assumptions!$C$8-13)))/C30,0) -> 0.47339276 | I30: =IFERROR(INDEX(Lookup!$C$7:$C$17,MATCH($B30,Lookup!$B$7:$B$17,0)),0) -> 0.478 | J30: =IFERROR(INDEX(Lookup!$D$7:$D$17,MATCH($B30,Lookup!$B$7:$B$17,0)),"") -> Store Manager
B31: Frozen | C31: =SUMIFS(Raw!$D$2:$D$397,Raw!$C$2:$C$397,"Actual",Raw!$B$2:$B$397,$B31,Raw!$A$2:$A$397,">="&EDATE(Assumptions!$C$7,-12),Raw!$A$2:$A$397,"<="&EDATE(Assumptions!$C$7,Assumptions!$C$8-13))+SUMIFS(Raw!$D$2:$D$397,Raw!$C$2:$C$397,"Outlook",Raw!$B$2:$B$397,$B31,Raw!$A$2:$A$397,">="&EDATE(Assumptions!$C$7,-12),Raw!$A$2:$A$397,"<="&EDATE(Assumptions!$C$7,Assumptions!$C$8-13)) -> 16684.75 | D31: =C31*(1+Assumptions!$C$6) -> 17352.14 | E31: =SUMIFS(Raw!$D$2:$D$397,Raw!$C$2:$C$397,"Forecast",Raw!$B$2:$B$397,$B31,Raw!$A$2:$A$397,">="&Assumptions!$C$7,Raw!$A$2:$A$397,"<="&EDATE(Assumptions!$C$7,Assumptions!$C$8-1)) -> 18122.14 | F31: =E31-D31 -> 770 | G31: =IFERROR(F31/D31,0) -> 0.04437493 | H31: =IFERROR((SUMIFS(Raw!$E$2:$E$397,Raw!$C$2:$C$397,"Actual",Raw!$B$2:$B$397,$B31,Raw!$A$2:$A$397,">="&EDATE(Assumptions!$C$7,-12),Raw!$A$2:$A$397,"<="&EDATE(Assumptions!$C$7,Assumptions!$C$8-13))+SUMIFS(Raw!$E$2:$E$397,Raw!$C$2:$C$397,"Outlook",Raw!$B$2:$B$397,$B31,Raw!$A$2:$A$397,">="&EDATE(Assumptions!$C$7,-12),Raw!$A$2:$A$397,"<="&EDATE(Assumptions!$C$7,Assumptions!$C$8-13)))/C31,0) -> 0.44343188 | I31: =IFERROR(INDEX(Lookup!$C$7:$C$17,MATCH($B31,Lookup!$B$7:$B$17,0)),0) -> 0.436 | J31: =IFERROR(INDEX(Lookup!$D$7:$D$17,MATCH($B31,Lookup!$B$7:$B$17,0)),"") -> Duty Manager
B32: Grocery | C32: =SUMIFS(Raw!$D$2:$D$397,Raw!$C$2:$C$397,"Actual",Raw!$B$2:$B$397,$B32,Raw!$A$2:$A$397,">="&EDATE(Assumptions!$C$7,-12),Raw!$A$2:$A$397,"<="&EDATE(Assumptions!$C$7,Assumptions!$C$8-13))+SUMIFS(Raw!$D$2:$D$397,Raw!$C$2:$C$397,"Outlook",Raw!$B$2:$B$397,$B32,Raw!$A$2:$A$397,">="&EDATE(Assumptions!$C$7,-12),Raw!$A$2:$A$397,"<="&EDATE(Assumptions!$C$7,Assumptions!$C$8-13)) -> 22900.19 | D32: =C32*(1+Assumptions!$C$6) -> 23816.198 | E32: =SUMIFS(Raw!$D$2:$D$397,Raw!$C$2:$C$397,"Forecast",Raw!$B$2:$B$397,$B32,Raw!$A$2:$A$397,">="&Assumptions!$C$7,Raw!$A$2:$A$397,"<="&EDATE(Assumptions!$C$7,Assumptions!$C$8-1)) -> 23957.31 | F32: =E32-D32 -> 141.1124 | G32: =IFERROR(F32/D32,0) -> 0.00592506 | H32: =IFERROR((SUMIFS(Raw!$E$2:$E$397,Raw!$C$2:$C$397,"Actual",Raw!$B$2:$B$397,$B32,Raw!$A$2:$A$397,">="&EDATE(Assumptions!$C$7,-12),Raw!$A$2:$A$397,"<="&EDATE(Assumptions!$C$7,Assumptions!$C$8-13))+SUMIFS(Raw!$E$2:$E$397,Raw!$C$2:$C$397,"Outlook",Raw!$B$2:$B$397,$B32,Raw!$A$2:$A$397,">="&EDATE(Assumptions!$C$7,-12),Raw!$A$2:$A$397,"<="&EDATE(Assumptions!$C$7,Assumptions!$C$8-13)))/C32,0) -> 0.3424072 | I32: =IFERROR(INDEX(Lookup!$C$7:$C$17,MATCH($B32,Lookup!$B$7:$B$17,0)),0) -> 0.348 | J32: =IFERROR(INDEX(Lookup!$D$7:$D$17,MATCH($B32,Lookup!$B$7:$B$17,0)),"") -> Duty Manager
B33: Health & Beauty | C33: =SUMIFS(Raw!$D$2:$D$397,Raw!$C$2:$C$397,"Actual",Raw!$B$2:$B$397,$B33,Raw!$A$2:$A$397,">="&EDATE(Assumptions!$C$7,-12),Raw!$A$2:$A$397,"<="&EDATE(Assumptions!$C$7,Assumptions!$C$8-13))+SUMIFS(Raw!$D$2:$D$397,Raw!$C$2:$C$397,"Outlook",Raw!$B$2:$B$397,$B33,Raw!$A$2:$A$397,">="&EDATE(Assumptions!$C$7,-12),Raw!$A$2:$A$397,"<="&EDATE(Assumptions!$C$7,Assumptions!$C$8-13)) -> 4395.03 | D33: =C33*(1+Assumptions!$C$6) -> 4570.8312 | E33: =SUMIFS(Raw!$D$2:$D$397,Raw!$C$2:$C$397,"Forecast",Raw!$B$2:$B$397,$B33,Raw!$A$2:$A$397,">="&Assumptions!$C$7,Raw!$A$2:$A$397,"<="&EDATE(Assumptions!$C$7,Assumptions!$C$8-1)) -> 4786.29 | F33: =E33-D33 -> 215.4588 | G33: =IFERROR(F33/D33,0) -> 0.047137772 | H33: =IFERROR((SUMIFS(Raw!$E$2:$E$397,Raw!$C$2:$C$397,"Actual",Raw!$B$2:$B$397,$B33,Raw!$A$2:$A$397,">="&EDATE(Assumptions!$C$7,-12),Raw!$A$2:$A$397,"<="&EDATE(Assumptions!$C$7,Assumptions!$C$8-13))+SUMIFS(Raw!$E$2:$E$397,Raw!$C$2:$C$397,"Outlook",Raw!$B$2:$B$397,$B33,Raw!$A$2:$A$397,">="&EDATE(Assumptions!$C$7,-12),Raw!$A$2:$A$397,"<="&EDATE(Assumptions!$C$7,Assumptions!$C$8-13)))/C33,0) -> 0.48869519 | I33: =IFERROR(INDEX(Lookup!$C$7:$C$17,MATCH($B33,Lookup!$B$7:$B$17,0)),0) -> 0.501 | J33: =IFERROR(INDEX(Lookup!$D$7:$D$17,MATCH($B33,Lookup!$B$7:$B$17,0)),"") -> Store Manager
B34: Household | C34: =SUMIFS(Raw!$D$2:$D$397,Raw!$C$2:$C$397,"Actual",Raw!$B$2:$B$397,$B34,Raw!$A$2:$A$397,">="&EDATE(Assumptions!$C$7,-12),Raw!$A$2:$A$397,"<="&EDATE(Assumptions!$C$7,Assumptions!$C$8-13))+SUMIFS(Raw!$D$2:$D$397,Raw!$C$2:$C$397,"Outlook",Raw!$B$2:$B$397,$B34,Raw!$A$2:$A$397,">="&EDATE(Assumptions!$C$7,-12),Raw!$A$2:$A$397,"<="&EDATE(Assumptions!$C$7,Assumptions!$C$8-13)) -> 7048.42 | D34: =C34*(1+Assumptions!$C$6) -> 7330.3568 | E34: =SUMIFS(Raw!$D$2:$D$397,Raw!$C$2:$C$397,"Forecast",Raw!$B$2:$B$397,$B34,Raw!$A$2:$A$397,">="&Assumptions!$C$7,Raw!$A$2:$A$397,"<="&EDATE(Assumptions!$C$7,Assumptions!$C$8-1)) -> 7226.08 | F34: =E34-D34 -> -104.2768 | G34: =IFERROR(F34/D34,0) -> -0.014225338 | H34: =IFERROR((SUMIFS(Raw!$E$2:$E$397,Raw!$C$2:$C$397,"Actual",Raw!$B$2:$B$397,$B34,Raw!$A$2:$A$397,">="&EDATE(Assumptions!$C$7,-12),Raw!$A$2:$A$397,"<="&EDATE(Assumptions!$C$7,Assumptions!$C$8-13))+SUMIFS(Raw!$E$2:$E$397,Raw!$C$2:$C$397,"Outlook",Raw!$B$2:$B$397,$B34,Raw!$A$2:$A$397,">="&EDATE(Assumptions!$C$7,-12),Raw!$A$2:$A$397,"<="&EDATE(Assumptions!$C$7,Assumptions!$C$8-13)))/C34,0) -> 0.40406502 | I34: =IFERROR(INDEX(Lookup!$C$7:$C$17,MATCH($B34,Lookup!$B$7:$B$17,0)),0) -> 0.412 | J34: =IFERROR(INDEX(Lookup!$D$7:$D$17,MATCH($B34,Lookup!$B$7:$B$17,0)),"") -> Duty Manager
B35: Produce | C35: =SUMIFS(Raw!$D$2:$D$397,Raw!$C$2:$C$397,"Actual",Raw!$B$2:$B$397,$B35,Raw!$A$2:$A$397,">="&EDATE(Assumptions!$C$7,-12),Raw!$A$2:$A$397,"<="&EDATE(Assumptions!$C$7,Assumptions!$C$8-13))+SUMIFS(Raw!$D$2:$D$397,Raw!$C$2:$C$397,"Outlook",Raw!$B$2:$B$397,$B35,Raw!$A$2:$A$397,">="&EDATE(Assumptions!$C$7,-12),Raw!$A$2:$A$397,"<="&EDATE(Assumptions!$C$7,Assumptions!$C$8-13)) -> 6611.57 | D35: =C35*(1+Assumptions!$C$6) -> 6876.0328 | E35: =SUMIFS(Raw!$D$2:$D$397,Raw!$C$2:$C$397,"Forecast",Raw!$B$2:$B$397,$B35,Raw!$A$2:$A$397,">="&Assumptions!$C$7,Raw!$A$2:$A$397,"<="&EDATE(Assumptions!$C$7,Assumptions!$C$8-1)) -> 7334.84 | F35: =E35-D35 -> 458.8072 | G35: =IFERROR(F35/D35,0) -> 0.066725569 | H35: =IFERROR((SUMIFS(Raw!$E$2:$E$397,Raw!$C$2:$C$397,"Actual",Raw!$B$2:$B$397,$B35,Raw!$A$2:$A$397,">="&EDATE(Assumptions!$C$7,-12),Raw!$A$2:$A$397,"<="&EDATE(Assumptions!$C$7,Assumptions!$C$8-13))+SUMIFS(Raw!$E$2:$E$397,Raw!$C$2:$C$397,"Outlook",Raw!$B$2:$B$397,$B35,Raw!$A$2:$A$397,">="&EDATE(Assumptions!$C$7,-12),Raw!$A$2:$A$397,"<="&EDATE(Assumptions!$C$7,Assumptions!$C$8-13)))/C35,0) -> 0.43220445 | I35: =IFERROR(INDEX(Lookup!$C$7:$C$17,MATCH($B35,Lookup!$B$7:$B$17,0)),0) -> 0.431 | J35: =IFERROR(INDEX(Lookup!$D$7:$D$17,MATCH($B35,Lookup!$B$7:$B$17,0)),"") -> Duty Manager
B36: Snacks & Confectionery | C36: =SUMIFS(Raw!$D$2:$D$397,Raw!$C$2:$C$397,"Actual",Raw!$B$2:$B$397,$B36,Raw!$A$2:$A$397,">="&EDATE(Assumptions!$C$7,-12),Raw!$A$2:$A$397,"<="&EDATE(Assumptions!$C$7,Assumptions!$C$8-13))+SUMIFS(Raw!$D$2:$D$397,Raw!$C$2:$C$397,"Outlook",Raw!$B$2:$B$397,$B36,Raw!$A$2:$A$397,">="&EDATE(Assumptions!$C$7,-12),Raw!$A$2:$A$397,"<="&EDATE(Assumptions!$C$7,Assumptions!$C$8-13)) -> 24828.95 | D36: =C36*(1+Assumptions!$C$6) -> 25822.108 | E36: =SUMIFS(Raw!$D$2:$D$397,Raw!$C$2:$C$397,"Forecast",Raw!$B$2:$B$397,$B36,Raw!$A$2:$A$397,">="&Assumptions!$C$7,Raw!$A$2:$A$397,"<="&EDATE(Assumptions!$C$7,Assumptions!$C$8-1)) -> 26325.14 | F36: =E36-D36 -> 503.032 | G36: =IFERROR(F36/D36,0) -> 0.019480671 | H36: =IFERROR((SUMIFS(Raw!$E$2:$E$397,Raw!$C$2:$C$397,"Actual",Raw!$B$2:$B$397,$B36,Raw!$A$2:$A$397,">="&EDATE(Assumptions!$C$7,-12),Raw!$A$2:$A$397,"<="&EDATE(Assumptions!$C$7,Assumptions!$C$8-13))+SUMIFS(Raw!$E$2:$E$397,Raw!$C$2:$C$397,"Outlook",Raw!$B$2:$B$397,$B36,Raw!$A$2:$A$397,">="&EDATE(Assumptions!$C$7,-12),Raw!$A$2:$A$397,"<="&EDATE(Assumptions!$C$7,Assumptions!$C$8-13)))/C36,0) -> 0.43965009 | I36: =IFERROR(INDEX(Lookup!$C$7:$C$17,MATCH($B36,Lookup!$B$7:$B$17,0)),0) -> 0.443 | J36: =IFERROR(INDEX(Lookup!$D$7:$D$17,MATCH($B36,Lookup!$B$7:$B$17,0)),"") -> Duty Manager
B37: Total | C37: =SUM(C26:C36) -> 268160.34 | D37: =SUM(D26:D36) -> 278886.75 | E37: =SUM(E26:E36) -> 279339.13 | F37: =SUM(F26:F36) -> 452.3764 | G37: =IFERROR(F37/D37,0) -> 0.0016220792

Sheet Pivot
B1: SHELLY
B2: Pivot tables
B3: Real Excel PivotTables over the Raw sheet: drag fields in the PivotTable pane to explore. They refresh when the file opens.
A5: Sales by category and month (filter Type: Actual / Forecast)
A6: Type | B6: (All)
A8: Row Labels | B8: Sales
A9: Bakery | B9: 171320.96
A10: Beer & Wine | B10: 366472.11
A11: Beverages | B11: 464156.13
A12: Dairy | B12: 499080.97
A13: Food To Go | B13: 554398.95
A14: Frozen | B14: 213197.97
A15: Grocery | B15: 299545.45
A16: Health & Beauty | B16: 52486.59
A17: Household | B17: 83265.65
A18: Produce | B18: 72231.85
A19: Snacks & Confectionery | B19: 309967.73
A20: Grand Total | B20: 3086124.4
A24: Sales by month and type
A25: Sales | B25: Column Labels
A26: Row Labels | B26: Actual | C26: Forecast | D26: Outlook | E26: Grand Total
A27: 2024-11-01 | B27: 83187.89 | C27: 0 | D27: 0 | E27: 83187.89
A28: 2024-12-01 | B28: 94755.88 | C28: 0 | D28: 0 | E28: 94755.88
A29: 2025-01-01 | B29: 80738.14 | C29: 0 | D29: 0 | E29: 80738.14
A30: 2025-02-01 | B30: 81306.55 | C30: 0 | D30: 0 | E30: 81306.55
A31: 2025-03-01 | B31: 86028.86 | C31: 0 | D31: 0 | E31: 86028.86
A32: 2025-04-01 | B32: 79207.3 | C32: 0 | D32: 0 | E32: 79207.3
A33: 2025-05-01 | B33: 82604.11 | C33: 0 | D33: 0 | E33: 82604.11
A34: 2025-06-01 | B34: 75752.63 | C34: 0 | D34: 0 | E34: 75752.63
A35: 2025-07-01 | B35: 78803.3 | C35: 0 | D35: 0 | E35: 78803.3
A36: 2025-08-01 | B36: 79656.08 | C36: 0 | D36: 0 | E36: 79656.08
A37: 2025-09-01 | B37: 79394.25 | C37: 0 | D37: 0 | E37: 79394.25
A38: 2025-10-01 | B38: 87343.9 | C38: 0 | D38: 0 | E38: 87343.9
... A63: Grand Total | B63: 1927804.6 | C63: 1070277.1 | D63: 88042.66 | E63: 3086124.4

Sheet Raw
A1: Month | B1: Category | C1: Type | D1: Sales | E1: Gross margin | F1: Units | G1: Low | H1: High
A2: 45597 | B2: Bakery | C2: Actual | D2: 4266.73 | E2: 1656.43 | F2: 1037
A3: 45597 | B3: Beer & Wine | C3: Actual | D3: 10360.41 | E3: 3486.51 | F3: 539
A4: 45597 | B4: Beverages | C4: Actual | D4: 13983.33 | E4: 7084.88 | F4: 3483
A5: 45597 | B5: Dairy | C5: Actual | D5: 12950.12 | E5: 3637.42 | F5: 2216
A6: 45597 | B6: Food To Go | C6: Actual | D6: 14617.13 | E6: 6943.53 | F6: 1867
A7: 45597 | B7: Frozen | C7: Actual | D7: 5248.55 | E7: 2341.05 | F7: 845
A8: 45597 | B8: Grocery | C8: Actual | D8: 7957.65 | E8: 2733.85 | F8: 1285
A9: 45597 | B9: Health & Beauty | C9: Actual | D9: 1319.41 | E9: 649.21 | F9: 159
A10: 45597 | B10: Household | C10: Actual | D10: 2038.57 | E10: 846.67 | F10: 243
A11: 45597 | B11: Produce | C11: Actual | D11: 2085.77 | E11: 898.27 | F11: 1379
A12: 45597 | B12: Snacks & Confectionery | C12: Actual | D12: 8360.22 | E12: 3655.02 | F12: 1940
A13: 45627 | B13: Bakery | C13: Actual | D13: 4908.52 | E13: 1909.72 | F13: 1178
... A254: 46266 | B254: Snacks & Confectionery | C254: Actual | D254: 8991.67 | E254: 3999.17 | F254: 2069
A255: 46296 | B255: Bakery | C255: Outlook | D255: 4943.77 | E255: 1888.52 | G255: 4672.12 | H255: 5215.42
A256: 46296 | B256: Beer & Wine | C256: Outlook | D256: 10507.4 | E256: 3551.5 | G256: 9930.05 | H256: 11084.76
A257: 46296 | B257: Beverages | C257: Outlook | D257: 13540.3 | E257: 6905.55 | G257: 12796.3 | H257: 14284.3
A258: 46296 | B258: Dairy | C258: Outlook | D258: 13890.05 | E258: 3861.43 | G258: 13126.83 | H258: 14653.27
A259: 46296 | B259: Food To Go | C259: Outlook | D259: 15410.67 | E259: 7366.3 | G259: 14563.9 | H259: 16257.45
A260: 46296 | B260: Frozen | C260: Outlook | D260: 6307.83 | E260: 2750.21 | G260: 5961.23 | H260: 6654.43
A261: 46296 | B261: Grocery | C261: Outlook | D261: 8471.63 | E261: 2948.13 | G261: 8006.13 | H261: 8937.12
A262: 46296 | B262: Health & Beauty | C262: Outlook | D262: 1380.67 | E262: 691.71 | G262: 1304.8 | H262: 1456.53
A263: 46296 | B263: Household | C263: Outlook | D263: 2484.78 | E263: 1023.73 | G263: 2348.25 | H263: 2621.31
A264: 46296 | B264: Produce | C264: Outlook | D264: 2071.94 | E264: 893.01 | G264: 1958.09 | H264: 2185.79
A265: 46296 | B265: Snacks & Confectionery | C265: Outlook | D265: 9033.62 | E265: 4001.89 | G265: 8537.24 | H265: 9529.99
A266: 46327 | B266: Bakery | C266: Forecast | D266: 4723.24 | G266: 4463.71 | H266: 4982.77
A267: 46327 | B267: Beer & Wine | C267: Forecast | D267: 10550.96 | G267: 9971.21 | H267: 11130.71
A268: 46327 | B268: Beverages | C268: Forecast | D268: 14690.17 | G268: 13882.99 | H268: 15497.36
A269: 46327 | B269: Dairy | C269: Forecast | D269: 14884.88 | G269: 14067 | H269: 15702.77
A270: 46327 | B270: Food To Go | C270: Forecast | D270: 15677.09 | G270: 14815.67 | H270: 16538.5
A271: 46327 | B271: Frozen | C271: Forecast | D271: 5895.24 | G271: 5571.31 | H271: 6219.17
A272: 46327 | B272: Grocery | C272: Forecast | D272: 8195.29 | G272: 7744.98 | H272: 8645.6
A273: 46327 | B273: Health & Beauty | C273: Forecast | D273: 1462.96 | G273: 1382.58 | H273: 1543.35
A274: 46327 | B274: Household | C274: Forecast | D274: 2298.83 | G274: 2172.51 | H274: 2425.14
A275: 46327 | B275: Produce | C275: Forecast | D275: 2236.94 | G275: 2114.02 | H275: 2359.85
A276: 46327 | B276: Snacks & Confectionery | C276: Forecast | D276: 8614.55 | G276: 8141.2 | H276: 9087.9
A277: 46357 | B277: Bakery | C277: Forecast | D277: 5656.34 | G277: 5345.54 | H277: 5967.14
... A397: 46661 | B397: Snacks & Confectionery | C397: Forecast | D397: 9577.98 | G397: 9051.7 | H397: 10104.27

Sheet Lookup
B1: SHELLY
B2: Lookup tables
B3: Reference data used by INDEX-MATCH formulas in the Model sheet.
B5: targets | M5: Category list
B6: category | C6: gm_target_pct | D6: owner | E6: short_life | M6: All
B7: Bakery | C7: 0.382 | D7: Store Manager | E7: Yes | M7: Bakery
B8: Beer & Wine | C8: 0.338 | D8: Licence Manager | E8: No | M8: Beer & Wine
B9: Beverages | C9: 0.51 | D9: Duty Manager | E9: No | M9: Beverages
B10: Dairy | C10: 0.278 | D10: Duty Manager | E10: Yes | M10: Dairy
B11: Food To Go | C11: 0.478 | D11: Store Manager | E11: Yes | M11: Food To Go
B12: Frozen | C12: 0.436 | D12: Duty Manager | E12: No | M12: Frozen
B13: Grocery | C13: 0.348 | D13: Duty Manager | E13: No | M13: Grocery
B14: Health & Beauty | C14: 0.501 | D14: Store Manager | E14: No | M14: Health & Beauty
B15: Household | C15: 0.412 | D15: Duty Manager | E15: No | M15: Household
B16: Produce | C16: 0.431 | D16: Duty Manager | E16: Yes | M16: Produce
B17: Snacks & Confectionery | C17: 0.443 | D17: Duty Manager | E17: No | M17: Snacks & Confectionery

Sheet Assumptions
B1: SHELLY
B2: Assumptions
B3: Blue cells are inputs: change them and every sheet recalculates.
B5: Input | C5: Value | D5: Why / source
B6: Growth target vs last year | C6: 0.04 | D6: config.yaml › budget.growth_vs_last_year_pct
B7: Plan starts (first month) | C7: 46327 | D7: First whole month after the data date
B8: Months in plan | C8: 3 | D8: 1-12. KPI tiles and the category plan use this window

Sheet Notes
B1: SHELLY
B2: Notes, method and sign-off
B3: How the numbers were made, what each column means, and who approved it.
B5: About this workbook
C6: Store: Demo Neighbourhood Store (Eden Terrace format). Data to 11 Oct 2026. Shelly v1.19.0.
C7: Synthetic demo data.
C8: Change the blue Category cell on the Dashboard, or any blue input on Assumptions: every formula follows.
B10: Method
C11: Budget = last year's same month × (1 + growth target).
C12: Forecast = last year's same month × recent 12-week trend (capped ±15%), backtested; Low/High = 80% range.
C13: Outlook rows = the current part-month (actual month-to-date + forecast for the rest).
B15: Data dictionary (Raw sheet)
B16: Month | C16: First day of the month
B17: Category | C17: Product category
B18: Type | C18: Actual = history; Forecast = Shelly's plan months; Outlook = current month
B19: Sales | C19: Net sales excl. GST ($)
B20: Gross margin | C20: Sales − cost of goods ($), actuals only
B21: Units | C21: Units sold (actuals)
B22: Low / High | C22: 80% forecast range ($)
B24: Sign-off
B25: Growth target and budget approved | C25: Name: ____________ Date: ________ ☐ Approved ☐ Changes needed
B26: Category owners briefed on their numbers | C26: Name: ____________ Date: ________ ☐ Approved ☐ Changes needed
B28: Generated by Shelly on 11 Oct 2026 21:20
